{
  "source": "ne21.com",
  "sourceName": "世纪新能源网",
  "generatedAt": "2026-07-13T21:24:17+00:00",
  "lookbackHours": 48,
  "articles": [
    {
      "id": "ne21-737",
      "title": "CDM碳交易",
      "url": "https://www.ne21.com/news/list-737.html",
      "summary": "",
      "publishedAt": null,
      "source": "ne21.com"
    },
    {
      "id": "ne21-228957",
      "title": "​2026年全球储能版图重塑：海外大型储能项目哪家好",
      "url": "https://www.ne21.com/news/show-228957.html",
      "summary": "",
      "publishedAt": null,
      "source": "ne21.com"
    },
    {
      "id": "ne21-228956",
      "title": "​2026年组串式光伏逆变器厂家推荐：技术解析与行业全景对比",
      "url": "https://www.ne21.com/news/show-228956.html",
      "summary": "",
      "publishedAt": null,
      "source": "ne21.com"
    },
    {
      "id": "ne21-228954",
      "title": "​工商业储能系统技术解析：以阳光电源为核心的多维比较",
      "url": "https://www.ne21.com/news/show-228954.html",
      "summary": "",
      "publishedAt": null,
      "source": "ne21.com"
    },
    {
      "id": "ne21-228953",
      "title": "​2026年光伏逆变器厂家哪个比较好？一文看懂五大品牌与选型底层逻辑",
      "url": "https://www.ne21.com/news/show-228953.html",
      "summary": "",
      "publishedAt": null,
      "source": "ne21.com"
    },
    {
      "id": "ne21-228952",
      "title": "2026年光伏构网技术哪家好—主流厂商技术路线深度解析",
      "url": "https://www.ne21.com/news/show-228952.html",
      "summary": "",
      "publishedAt": null,
      "source": "ne21.com"
    }
  ],
  "stats": {
    "articleCount": 6
  },
  "errors": []
}
