{
  "generatedAt": "2026-06-02T23:52:59+00:00",
  "sources": [
    {
      "id": "bjx.com.cn",
      "name": "北极星电力网",
      "generatedAt": "2026-06-02T23:05:24+00:00",
      "articleCount": 0,
      "hasErrors": true
    },
    {
      "id": "china5e.com",
      "name": "中国能源网",
      "generatedAt": "2026-06-02T23:52:36+00:00",
      "articleCount": 51,
      "hasErrors": false
    },
    {
      "id": "chinapower.org.cn",
      "name": "中国电力网",
      "generatedAt": "2026-06-02T23:52:59+00:00",
      "articleCount": 4,
      "hasErrors": false
    },
    {
      "id": "cjys.net",
      "name": "长江有色金属现货报价",
      "generatedAt": "2026-06-02T23:52:27+00:00",
      "articleCount": 0,
      "hasErrors": false
    },
    {
      "id": "cpnn.com.cn",
      "name": "电网头条（中国能源传媒集团）",
      "generatedAt": "2026-06-02T23:52:25+00:00",
      "articleCount": 75,
      "hasErrors": false
    },
    {
      "id": "iesplaza.com",
      "name": "IESPlaza 综合能源服务网",
      "generatedAt": "2026-06-02T23:52:34+00:00",
      "articleCount": 0,
      "hasErrors": true
    },
    {
      "id": "ne21.com",
      "name": "世纪新能源网",
      "generatedAt": "2026-06-02T23:05:32+00:00",
      "articleCount": 0,
      "hasErrors": true
    },
    {
      "id": "nea.gov.cn",
      "name": "国家能源局",
      "generatedAt": "2026-06-02T23:52:26+00:00",
      "articleCount": 53,
      "hasErrors": false
    },
    {
      "id": "xinhuanet.com",
      "name": "新华社能源频道",
      "generatedAt": "2026-06-02T23:52:38+00:00",
      "articleCount": 4,
      "hasErrors": false
    }
  ],
  "articles": [
    {
      "id": "china5e-1204528",
      "title": "华为周涛：构建智能世界的绿电驱动力",
      "url": "https://www.china5e.com/news/news-1204528-1.html",
      "summary": "周涛表示：“在技术创新与政策环境的双重驱动下，新能源产业正迎来价值重构，迈入价值深耕的新阶段。面向新型电力系统加速演进的趋势，华为数字能源聚焦4T技术，与客户、伙伴一起，以需求驱动技术、以场景定义解决方案，推动产业可持续发展，加速新能源成为主力电源，支撑新型电力系统构建。”",
      "publishedAt": "2026-06-02",
      "source": "china5e.com"
    },
    {
      "id": "china5e-1204518",
      "title": "2026年能源网络通信创新应用大会（辽宁大连）举行",
      "url": "https://www.china5e.com/news/news-1204518-1.html",
      "summary": "中国企业投资协会、清华大学创新发展研究院、中国能源研究会分布式能源专业委员会与中国能源网共同举办的--> “2017（第十三届）中国能源战略投资论坛暨'我能'创新火炬奖颁奖典礼”--> http://www.china5e.com/subject/show_1061.html",
      "publishedAt": "2026-06-02",
      "source": "china5e.com"
    },
    {
      "id": "china5e-1204524",
      "title": "2026北方重大工程线缆应用案例与企业资质",
      "url": "https://www.china5e.com/news/news-1204524-1.html",
      "summary": "2026年，津达线缆在北方地区多项重大工程持续推进，包括京津冀协同发展项目、东北老工业基地振兴项目、西北新能源大基地开发、城市轨道交通网络扩展等。这些重大工程项目对线缆产品的质量、供应能力、技术支撑和售后服务都提出了较高要求。本文梳理北方地区重大工程的线缆应用情况，对相关企业的资",
      "publishedAt": "2026-06-02",
      "source": "china5e.com"
    },
    {
      "id": "china5e-1204485",
      "title": "山西焦煤(000983)：主产地合规性控产加剧 看好焦煤价格上涨带来公司业绩回升",
      "url": "https://www.china5e.com/news/news-1204485-1.html",
      "summary": "2026 年5 月22 日，山西省长治市沁源县山西通洲集团留神峪煤业井下发生重大瓦斯爆炸事故，造成重大人员伤亡，随后国务院成立事故调查组，预计山西等主产地将维持高强度安监。",
      "publishedAt": "2026-06-02",
      "source": "china5e.com"
    },
    {
      "id": "china5e-1204484",
      "title": "湖北能源(000883)：提分红比例至不低于50% 26Q1来水偏丰业绩高增",
      "url": "https://www.china5e.com/news/news-1204484-1.html",
      "summary": "事件：1)公司发布2025 年年报，2025 年实现归母净利润19.09 亿元，同比增长5.26%;实现扣非归母净利润11.62 亿元，同比下降33.64%;2)公司发布2026 年一季报，2026Q1 实现归母净利润5.06 亿元，同比增长42.04%;实现扣非归母净利润4.4",
      "publishedAt": "2026-06-02",
      "source": "china5e.com",
      "province": "湖北"
    },
    {
      "id": "china5e-1204526",
      "title": "国网晋中市榆次区供电分公司：全力以赴保供电 暖心护航高考路",
      "url": "https://www.china5e.com/news/news-1204526-1.html",
      "summary": "中国企业投资协会、清华大学创新发展研究院、中国能源研究会分布式能源专业委员会与中国能源网共同举办的--> “2017（第十三届）中国能源战略投资论坛暨'我能'创新火炬奖颁奖典礼”--> http://www.china5e.com/subject/show_1061.html",
      "publishedAt": "2026-06-02",
      "source": "china5e.com"
    },
    {
      "id": "china5e-1204525",
      "title": "国网福建电力发布全面打造“双满意”现代化电力营商环境20项服务举措",
      "url": "https://www.china5e.com/news/news-1204525-1.html",
      "summary": "2026年是“十五五”规划开局之年，国网福建电力以“让人民群众满意、让党和政府满意”为总目标，在“可靠、便捷、绿色、贴心”四个能力上追求领先，确保到2030年全面建成办电快捷化、服务数智化、供电高质化、用电绿色化、服务普惠化、信息透明化的“双满意”现代化电力营商环境，以电力之优助",
      "publishedAt": "2026-06-02",
      "source": "china5e.com"
    },
    {
      "id": "china5e-1204519",
      "title": "安徽明光：电力护航 伴童成长",
      "url": "https://www.china5e.com/news/news-1204519-1.html",
      "summary": "中国企业投资协会、清华大学创新发展研究院、中国能源研究会分布式能源专业委员会与中国能源网共同举办的--> “2017（第十三届）中国能源战略投资论坛暨'我能'创新火炬奖颁奖典礼”--> http://www.china5e.com/subject/show_1061.html",
      "publishedAt": "2026-06-02",
      "source": "china5e.com",
      "province": "安徽"
    },
    {
      "id": "china5e-1204517",
      "title": "国网吕梁供电公司：严守合规底线 精耕优质服务",
      "url": "https://www.china5e.com/news/news-1204517-1.html",
      "summary": "中国企业投资协会、清华大学创新发展研究院、中国能源研究会分布式能源专业委员会与中国能源网共同举办的--> “2017（第十三届）中国能源战略投资论坛暨'我能'创新火炬奖颁奖典礼”--> http://www.china5e.com/subject/show_1061.html",
      "publishedAt": "2026-06-02",
      "source": "china5e.com"
    },
    {
      "id": "china5e-1204495",
      "title": "大渡河两个水电站投产",
      "url": "https://www.china5e.com/news/news-1204495-1.html",
      "summary": "中国企业投资协会、清华大学创新发展研究院、中国能源研究会分布式能源专业委员会与中国能源网共同举办的--> “2017（第十三届）中国能源战略投资论坛暨'我能'创新火炬奖颁奖典礼”--> http://www.china5e.com/subject/show_1061.html",
      "publishedAt": "2026-06-02",
      "source": "china5e.com"
    },
    {
      "id": "china5e-1204530",
      "title": "为恒智能打造AI-native智能能源操作系统 WHES OS，实测收益提升13.49%",
      "url": "https://www.china5e.com/news/news-1204530-1.html",
      "summary": "中国企业投资协会、清华大学创新发展研究院、中国能源研究会分布式能源专业委员会与中国能源网共同举办的--> “2017（第十三届）中国能源战略投资论坛暨'我能'创新火炬奖颁奖典礼”--> http://www.china5e.com/subject/show_1061.html",
      "publishedAt": "2026-06-02",
      "source": "china5e.com"
    },
    {
      "id": "china5e-1204529",
      "title": "晶科能源新任 CEO 首亮相， 重磅发布全新一代高效光储解决方案",
      "url": "https://www.china5e.com/news/news-1204529-1.html",
      "summary": "中国企业投资协会、清华大学创新发展研究院、中国能源研究会分布式能源专业委员会与中国能源网共同举办的--> “2017（第十三届）中国能源战略投资论坛暨'我能'创新火炬奖颁奖典礼”--> http://www.china5e.com/subject/show_1061.html",
      "publishedAt": "2026-06-02",
      "source": "china5e.com"
    },
    {
      "id": "china5e-1204520",
      "title": "长虹能源丨全极耳圆柱锂电标杆，深耕工具、小动力与智能装备赛道",
      "url": "https://www.china5e.com/news/news-1204520-1.html",
      "summary": "四川长虹新能源科技股份有限公司成立于2006年,是长虹控股集团旗下国家级高新技术企业、国家级专精特新“小巨人”、国家级绿色工厂,构建了“碱锰电池+锂电池”双轮驱动的核心产业格局,业务覆盖电池研发、智造、销售全链条,拥有295项核心专利技术,行业标准制定话语权突出。",
      "publishedAt": "2026-06-02",
      "source": "china5e.com"
    },
    {
      "id": "china5e-1204506",
      "title": "中广核吉水县枫江镇70MW农光互补项目全容量并网",
      "url": "https://www.china5e.com/news/news-1204506-1.html",
      "summary": "5月31日，中广核吉水县枫江镇70兆瓦农光互补项目全容量并网发电，对促进地方经济发展、优化能源结构具有积极作用，社会效益和环境效益显著。",
      "publishedAt": "2026-06-02",
      "source": "china5e.com"
    },
    {
      "id": "china5e-1204505",
      "title": "浙江舟山106.25MW风电改造升级项目全容量并网",
      "url": "https://www.china5e.com/news/news-1204505-1.html",
      "summary": "北极星风力发电网获悉，2026年5月31日，随着衢电3505线成功合闸，舟山衢山风力发电场改造升级项目实现全容量并网。总容量106.25兆瓦的17台风力发电机组全部投入运行，持续源源不断地为国家输送清洁能源。",
      "publishedAt": "2026-06-02",
      "source": "china5e.com"
    },
    {
      "id": "china5e-1204523",
      "title": "《中国油气与新能源市场发展报告（2026）》发布",
      "url": "https://www.china5e.com/news/news-1204523-1.html",
      "summary": "中国企业投资协会、清华大学创新发展研究院、中国能源研究会分布式能源专业委员会与中国能源网共同举办的--> “2017（第十三届）中国能源战略投资论坛暨'我能'创新火炬奖颁奖典礼”--> http://www.china5e.com/subject/show_1061.html",
      "publishedAt": "2026-06-02",
      "source": "china5e.com"
    },
    {
      "id": "china5e-1204493",
      "title": "美国战略石油储备降至两年多来最低水平",
      "url": "https://www.china5e.com/news/news-1204493-1.html",
      "summary": "中国企业投资协会、清华大学创新发展研究院、中国能源研究会分布式能源专业委员会与中国能源网共同举办的--> “2017（第十三届）中国能源战略投资论坛暨'我能'创新火炬奖颁奖典礼”--> http://www.china5e.com/subject/show_1061.html",
      "publishedAt": "2026-06-02",
      "source": "china5e.com"
    },
    {
      "id": "china5e-1204487",
      "title": "国际油价6月1日大幅上涨",
      "url": "https://www.china5e.com/news/news-1204487-1.html",
      "summary": "中国企业投资协会、清华大学创新发展研究院、中国能源研究会分布式能源专业委员会与中国能源网共同举办的--> “2017（第十三届）中国能源战略投资论坛暨'我能'创新火炬奖颁奖典礼”--> http://www.china5e.com/subject/show_1061.html",
      "publishedAt": "2026-06-02",
      "source": "china5e.com"
    },
    {
      "id": "china5e-1204486",
      "title": "山西前4个月非常规天然气产量同比增长14%",
      "url": "https://www.china5e.com/news/news-1204486-1.html",
      "summary": "中国企业投资协会、清华大学创新发展研究院、中国能源研究会分布式能源专业委员会与中国能源网共同举办的--> “2017（第十三届）中国能源战略投资论坛暨'我能'创新火炬奖颁奖典礼”--> http://www.china5e.com/subject/show_1061.html",
      "publishedAt": "2026-06-02",
      "source": "china5e.com"
    },
    {
      "id": "china5e-1204522",
      "title": "征服东方达喀尔，长城润滑油护航环塔极限征途",
      "url": "https://www.china5e.com/news/news-1204522-1.html",
      "summary": "大美新疆，勇士凯旋。6月1日，被誉为“东方达喀尔”的2026中国环塔国际拉力赛在历经19天、近8000公里的艰苦历练后，于新疆阿克苏市圆满落下帷幕。在这场史上最长、考验严峻的越野盛宴中，钢铁与黄沙激烈碰撞，挑战与意志全力交锋。",
      "publishedAt": "2026-06-02",
      "source": "china5e.com"
    },
    {
      "id": "china5e-1204514",
      "title": "印尼煤炭“国家专营”落地，全球煤市迎来新变局?",
      "url": "https://www.china5e.com/news/news-1204514-1.html",
      "summary": "当全球还在消化地缘冲突带来的能源冲击时，来自印度尼西亚共和国(以下简称“印尼”)的一纸新政，让本已紧绷的国际煤炭市场再添波澜。",
      "publishedAt": "2026-06-02",
      "source": "china5e.com"
    },
    {
      "id": "china5e-1204513",
      "title": "印尼煤小船报价升至70美金之上",
      "url": "https://www.china5e.com/news/news-1204513-1.html",
      "summary": "亚洲动力煤市场卖方报价保持坚挺，在我国国内煤炭供应扰动、印尼煤出口政策前景不明朗的背景下，市场整体氛围偏强，不过终端用户采购仍偏谨慎，实际成交依旧偏少。",
      "publishedAt": "2026-06-02",
      "source": "china5e.com"
    },
    {
      "id": "china5e-1204512",
      "title": "MTB：陕蒙坑口降价5-20元，焦煤涨停、焦炭第五轮提涨落地",
      "url": "https://www.china5e.com/news/news-1204512-1.html",
      "summary": "6月的第一天，当陕蒙坑口传来部分煤矿下调5–20元/吨的消息时，北港各个动力煤指数再次上涨3-5元/吨，无烟煤价格却上涨30-100元，焦煤期货在午盘强势涨停，涨幅 7.63%，报 1383元/吨(山西冶金煤竞拍今日最高上涨120元/吨);与此同时，焦炭第五轮提涨正式落地——自6",
      "publishedAt": "2026-06-02",
      "source": "china5e.com"
    },
    {
      "id": "china5e-1204511",
      "title": "侯月铁路开始集中修施工",
      "url": "https://www.china5e.com/news/news-1204511-1.html",
      "summary": "侯月铁路起于山西侯马，终于河南月山，是晋煤外运的重要南部通道，年运输能力超1亿吨，是连接晋豫两省的能源运输大动脉。",
      "publishedAt": "2026-06-02",
      "source": "china5e.com"
    },
    {
      "id": "china5e-1204510",
      "title": "2026年全球煤炭投资将增长4%，达到14年来新高",
      "url": "https://www.china5e.com/news/news-1204510-1.html",
      "summary": "据“未来煤炭”机构(FutureCoal，原世界煤炭协会)引述国际能源署(IEA)最近发布的《2026年世界能源投资》(World Energy Investment 2026)报告指出，IEA报告预计，2026年，全球包括煤炭生产及基础设施在内的供应方面的总投资将达到约1800",
      "publishedAt": "2026-06-02",
      "source": "china5e.com"
    },
    {
      "id": "china5e-1204490",
      "title": "《中国噪声污染防治报告（2026）》发布",
      "url": "https://www.china5e.com/news/news-1204490-1.html",
      "summary": "中国企业投资协会、清华大学创新发展研究院、中国能源研究会分布式能源专业委员会与中国能源网共同举办的--> “2017（第十三届）中国能源战略投资论坛暨'我能'创新火炬奖颁奖典礼”--> http://www.china5e.com/subject/show_1061.html",
      "publishedAt": "2026-06-02",
      "source": "china5e.com"
    },
    {
      "id": "china5e-1204521",
      "title": "中国智造 智驱全球｜小湾智能携旗舰光伏清扫机器人重磅亮相Intersolar Europe 2026慕尼黑光伏展",
      "url": "https://www.china5e.com/news/news-1204521-1.html",
      "summary": "慕尼黑，2026年6月 — 全球规模最大、影响力最强的光伏行业顶级盛会Intersolar Europe 2026(慕尼黑国际光伏展)，将于6月23日至25日在德国慕尼黑国际展览中心正式举办。作为国内AI光伏智能化运维领军企业、中国智造出海核心代表，深圳市小湾智能有限公司(Bay",
      "publishedAt": "2026-06-02",
      "source": "china5e.com"
    },
    {
      "id": "chinapower-459031",
      "title": "乌兰察布首批120万千瓦项目获2026年度水利电力行业优质工程",
      "url": "https://www.chinapower.org.cn/detail/459031.html",
      "summary": "近日，国家电投集团内蒙古公司察哈尔新能源公司乌兰察布风电基地一期600万千瓦示范项目首批120万千瓦本地消纳工程获中国水利电力质量管理协会公布的“水利电力行业优质工程”称号。",
      "publishedAt": "2026-06-02",
      "source": "chinapower.org.cn"
    },
    {
      "id": "chinapower-459024",
      "title": "南方电网上线首个设备健康诊断“数字医生”",
      "url": "https://www.chinapower.org.cn/detail/459024.html",
      "summary": "近日，南方电网首个设备健康诊断“数字医生”上线。该系统是南网科研院研发的多智能体协同的电力设备状态评价智能体，部署于南方电网生产指挥中心网级设备状态评价系统，标志着电力设备运维实现了从“人工经验驱动”到“闭环智能体驱动”的跨越，为工业领域实现多智能体协同应用落地提供标杆范例。",
      "publishedAt": "2026-06-02",
      "source": "chinapower.org.cn"
    },
    {
      "id": "chinapower-459023",
      "title": "南方总调发布电力通信全景支撑电网高质量发展技术白皮书",
      "url": "https://www.chinapower.org.cn/detail/459023.html",
      "summary": "5月28日，在中国能源研究会2026能源网络通信创新应用大会上，南方总调正式发布《智联电网·通信赋能——电力通信全景支撑电网高质量发展技术白皮书》。大会以“数智赋能通信创新，助力‘十五五’加快构建新型能源体系”为主题，汇聚行业专家、企业代表共话技术创新。南方总调相关负责人作主旨报",
      "publishedAt": "2026-06-02",
      "source": "chinapower.org.cn"
    },
    {
      "id": "chinapower-459011",
      "title": "人民日报客户端：复工复产 扎哈淖尔35万吨绿电铝项目“春耕”正忙",
      "url": "https://www.chinapower.org.cn/detail/459011.html",
      "summary": "",
      "publishedAt": "2026-06-02",
      "source": "chinapower.org.cn"
    },
    {
      "id": "cpnn-t20260602_1892296",
      "title": "我国非化石能源电力消费核算实现全国统一",
      "url": "https://www.cpnn.com.cn/news/xwtt/202606/t20260602_1892296.html",
      "summary": "",
      "publishedAt": "2026-06-02",
      "source": "cpnn.com.cn"
    },
    {
      "id": "cpnn-t20260602_1892456",
      "title": "两部门通知：在云霄直流开展输电权市场化交易",
      "url": "https://www.cpnn.com.cn/news/nytt/202606/t20260602_1892456.html",
      "summary": "",
      "publishedAt": "2026-06-02",
      "source": "cpnn.com.cn"
    },
    {
      "id": "cpnn-t20260602_1892301",
      "title": "专家解读文章︱构建非化石能源电力消费核算体系 为保障我国如期实现碳达峰提供方法支撑",
      "url": "https://www.cpnn.com.cn/news/nytt/202606/t20260602_1892301.html",
      "summary": "",
      "publishedAt": "2026-06-02",
      "source": "cpnn.com.cn"
    },
    {
      "id": "cpnn-t20260602_1892300",
      "title": "专家解读文章︱非化石能源电力消费核算方法出台 有力支撑碳排放双控制度落地实施",
      "url": "https://www.cpnn.com.cn/news/nytt/202606/t20260602_1892300.html",
      "summary": "",
      "publishedAt": "2026-06-02",
      "source": "cpnn.com.cn"
    },
    {
      "id": "cpnn-t20260602_1892169",
      "title": "全国“两优一先”名单，能源人表现亮眼！",
      "url": "https://www.cpnn.com.cn/news/hy/202606/t20260602_1892169.html",
      "summary": "",
      "publishedAt": "2026-06-02",
      "source": "cpnn.com.cn"
    },
    {
      "id": "cpnn-t20260602_1892215",
      "title": "响应监管要求 云南电网实现居民用户漏电监测全覆盖",
      "url": "https://www.cpnn.com.cn/news/nyjg/202606/t20260602_1892215.html",
      "summary": "",
      "publishedAt": "2026-06-02",
      "source": "cpnn.com.cn"
    },
    {
      "id": "cpnn-t20260602_1892213",
      "title": "福建能源监管办有序做好电力业务许可证延续工作",
      "url": "https://www.cpnn.com.cn/news/nyjg/202606/t20260602_1892213.html",
      "summary": "",
      "publishedAt": "2026-06-02",
      "source": "cpnn.com.cn"
    },
    {
      "id": "cpnn-t20260602_1892407",
      "title": "95.88亿！电投能源发行股份购买资产完成",
      "url": "https://www.cpnn.com.cn/news/dianli2023/202606/t20260602_1892407.html",
      "summary": "",
      "publishedAt": "2026-06-02",
      "source": "cpnn.com.cn"
    },
    {
      "id": "cpnn-t20260602_1892406",
      "title": "连板电力股提示算力业务风险",
      "url": "https://www.cpnn.com.cn/news/dianli2023/202606/t20260602_1892406.html",
      "summary": "",
      "publishedAt": "2026-06-02",
      "source": "cpnn.com.cn"
    },
    {
      "id": "cpnn-t20260602_1892405",
      "title": "辽宁徐大堡核电3号机组热试成功",
      "url": "https://www.cpnn.com.cn/news/dianli2023/202606/t20260602_1892405.html",
      "summary": "",
      "publishedAt": "2026-06-02",
      "source": "cpnn.com.cn"
    },
    {
      "id": "cpnn-t20260602_1892199",
      "title": "《中国油气与新能源市场发展报告（2026）》发布",
      "url": "https://www.cpnn.com.cn/news/yq/202606/t20260602_1892199.html",
      "summary": "",
      "publishedAt": "2026-06-02",
      "source": "cpnn.com.cn"
    },
    {
      "id": "cpnn-t20260602_1892306",
      "title": "宁夏迈入千万千瓦级储能大省行列",
      "url": "https://www.cpnn.com.cn/news/xny/202606/t20260602_1892306.html",
      "summary": "",
      "publishedAt": "2026-06-02",
      "source": "cpnn.com.cn"
    },
    {
      "id": "cpnn-t20260602_1892194",
      "title": "固废变资源 推动新能源产业“绿色循环”",
      "url": "https://www.cpnn.com.cn/news/xny/202606/t20260602_1892194.html",
      "summary": "",
      "publishedAt": "2026-06-02",
      "source": "cpnn.com.cn"
    },
    {
      "id": "cpnn-t20260602_1892143",
      "title": "绿色出行 引领低碳生活新风尚",
      "url": "https://www.cpnn.com.cn/news/ydylnyhz/202606/t20260602_1892143.html",
      "summary": "",
      "publishedAt": "2026-06-02",
      "source": "cpnn.com.cn"
    },
    {
      "id": "cpnn-t20260602_1892174",
      "title": "山西：立足能源、算力 加快推进“人工智能+”行动",
      "url": "https://www.cpnn.com.cn/news/dfny/202606/t20260602_1892174.html",
      "summary": "",
      "publishedAt": "2026-06-02",
      "source": "cpnn.com.cn"
    },
    {
      "id": "cpnn-t20260602_1892192",
      "title": "海南启动三年电力抄表到户改造",
      "url": "https://www.cpnn.com.cn/news/dfny/202606/t20260602_1892192.html",
      "summary": "",
      "publishedAt": "2026-06-02",
      "source": "cpnn.com.cn"
    },
    {
      "id": "cpnn-t20260602_1892290",
      "title": "广西电力科学技术协会揭牌成立",
      "url": "https://www.cpnn.com.cn/news/kj/202606/t20260602_1892290.html",
      "summary": "",
      "publishedAt": "2026-06-02",
      "source": "cpnn.com.cn"
    },
    {
      "id": "cpnn-t20260602_1892178",
      "title": "香港理工大学·月山能源新一代矿业联合实验室揭牌",
      "url": "https://www.cpnn.com.cn/news/kj/202606/t20260602_1892178.html",
      "summary": "",
      "publishedAt": "2026-06-02",
      "source": "cpnn.com.cn"
    },
    {
      "id": "cpnn-t20260602_1892155",
      "title": "担忧能源与供应链 美CEO信心指数大跌",
      "url": "https://www.cpnn.com.cn/news/gj/202606/t20260602_1892155.html",
      "summary": "",
      "publishedAt": "2026-06-02",
      "source": "cpnn.com.cn"
    },
    {
      "id": "cpnn-t20260602_1892168",
      "title": "扎波罗热核电站负责人：核电站存在安全隐患",
      "url": "https://www.cpnn.com.cn/news/gj/202606/t20260602_1892168.html",
      "summary": "",
      "publishedAt": "2026-06-02",
      "source": "cpnn.com.cn"
    },
    {
      "id": "cpnn-t20260602_1892288",
      "title": "经济日报：发力补上低碳产业短板",
      "url": "https://www.cpnn.com.cn/news/baogao2023/202606/t20260602_1892288.html",
      "summary": "",
      "publishedAt": "2026-06-02",
      "source": "cpnn.com.cn"
    },
    {
      "id": "cpnn-t20260602_1892294",
      "title": "财经观察：中企助力东南亚“绿电互联”",
      "url": "https://www.cpnn.com.cn/news/baogao2023/202606/t20260602_1892294.html",
      "summary": "",
      "publishedAt": "2026-06-02",
      "source": "cpnn.com.cn"
    },
    {
      "id": "cpnn-t20260602_1892303",
      "title": "非化石能源电力消费核算指南出台 绿证市场迎利好",
      "url": "https://www.cpnn.com.cn/news/baogao2023/202606/t20260602_1892303.html",
      "summary": "",
      "publishedAt": "2026-06-02",
      "source": "cpnn.com.cn"
    },
    {
      "id": "cpnn-t20260602_1892484",
      "title": "国网淮北供电：守护皖北能源“桥头堡”",
      "url": "https://www.cpnn.com.cn/qiye/dianwangPD2023/202606/t20260602_1892484.html",
      "summary": "",
      "publishedAt": "2026-06-02",
      "source": "cpnn.com.cn",
      "province": "安徽"
    },
    {
      "id": "cpnn-t20260602_1892333",
      "title": "国家能源集团在希腊举办企业开放日活动",
      "url": "https://www.cpnn.com.cn/qiye/fadianPD2023/202606/t20260602_1892333.html",
      "summary": "",
      "publishedAt": "2026-06-02",
      "source": "cpnn.com.cn"
    },
    {
      "id": "cpnn-t20260602_1892332",
      "title": "国能准东露天煤矿：一份写在车轮上的“零碳”答案",
      "url": "https://www.cpnn.com.cn/qiye/fadianPD2023/202606/t20260602_1892332.html",
      "summary": "",
      "publishedAt": "2026-06-02",
      "source": "cpnn.com.cn"
    },
    {
      "id": "cpnn-t20260602_1892316",
      "title": "国家能源集团龙源电力：“碳索者”的数字攻坚记",
      "url": "https://www.cpnn.com.cn/qiye/fadianPD2023/202606/t20260602_1892316.html",
      "summary": "",
      "publishedAt": "2026-06-02",
      "source": "cpnn.com.cn"
    },
    {
      "id": "cpnn-t20260602_1892334",
      "title": "杭州平晟电力：“电”亮童心 “育蕾”花开",
      "url": "https://www.cpnn.com.cn/qiye/yzfw/202606/t20260602_1892334.html",
      "summary": "",
      "publishedAt": "2026-06-02",
      "source": "cpnn.com.cn"
    },
    {
      "id": "cpnn-t20260602_1892481",
      "title": "大唐陕西水电事业部：电力科普进校园 星光相伴筑童梦",
      "url": "https://www.cpnn.com.cn/qiye/yzfw/202606/t20260602_1892481.html",
      "summary": "",
      "publishedAt": "2026-06-02",
      "source": "cpnn.com.cn"
    },
    {
      "id": "cpnn-t20260602_1892488",
      "title": "新能源领军千人计划 共筑产业发展新生态",
      "url": "https://www.cpnn.com.cn/qiye/jishu2023/202606/t20260602_1892488.html",
      "summary": "",
      "publishedAt": "2026-06-02",
      "source": "cpnn.com.cn"
    },
    {
      "id": "cpnn-t20260602_1892328",
      "title": "广西电力行业协会召开2026年会员大会暨第五届理事会第五次会议",
      "url": "https://www.cpnn.com.cn/qiye/zggdsPD2023/202606/t20260602_1892328.html",
      "summary": "",
      "publishedAt": "2026-06-02",
      "source": "cpnn.com.cn"
    },
    {
      "id": "cpnn-t20260602_1892330",
      "title": "国家能源集团连续九年获得定点帮扶工作成效考核“好”评价",
      "url": "https://www.cpnn.com.cn/qiye/rongyu/202606/t20260602_1892330.html",
      "summary": "",
      "publishedAt": "2026-06-02",
      "source": "cpnn.com.cn"
    },
    {
      "id": "nea-20260602-a7e494c0ee274b839b9febc63b74d861-c",
      "title": "国家能源局发布2026年4月全国可再生能源绿色电力证书核发及交易数据",
      "url": "https://www.nea.gov.cn/20260602/a7e494c0ee274b839b9febc63b74d861/c.html",
      "summary": "",
      "publishedAt": "2026-06-02",
      "source": "nea.gov.cn"
    },
    {
      "id": "nea-20260602-56b828c0ada84754973782e9e2348751-c",
      "title": "华北能源监管局主要负责同志拜会天津市常务副市长",
      "url": "https://www.nea.gov.cn/20260602/56b828c0ada84754973782e9e2348751/c.html",
      "summary": "",
      "publishedAt": "2026-06-02",
      "source": "nea.gov.cn"
    },
    {
      "id": "nea-20260602-d44936024f38492197816268b7fcae1b-c",
      "title": "东北能源监管局赴太平湾发电厂 开展汛前安全检查",
      "url": "https://www.nea.gov.cn/20260602/d44936024f38492197816268b7fcae1b/c.html",
      "summary": "",
      "publishedAt": "2026-06-02",
      "source": "nea.gov.cn"
    },
    {
      "id": "nea-20260602-3bdacabcf5794acbac0c85f5665e46f9-c",
      "title": "华东能源监管局开展供电企业信息公开情况非现场监管",
      "url": "https://www.nea.gov.cn/20260602/3bdacabcf5794acbac0c85f5665e46f9/c.html",
      "summary": "",
      "publishedAt": "2026-06-02",
      "source": "nea.gov.cn"
    },
    {
      "id": "nea-20260602-0d5bb79e7edf4c59b73d859f5830ae19-c",
      "title": "华中能源监管局组织召开新型经营主体参与电力市场工作座谈会",
      "url": "https://www.nea.gov.cn/20260602/0d5bb79e7edf4c59b73d859f5830ae19/c.html",
      "summary": "",
      "publishedAt": "2026-06-02",
      "source": "nea.gov.cn",
      "province": "华中"
    },
    {
      "id": "nea-20260602-378f944103254a459cf1fe677ad2c189-c",
      "title": "南方能源监管局率先落地新能源集中报价",
      "url": "https://www.nea.gov.cn/20260602/378f944103254a459cf1fe677ad2c189/c.html",
      "summary": "",
      "publishedAt": "2026-06-02",
      "source": "nea.gov.cn"
    },
    {
      "id": "nea-20260602-3b7979c3c6644484ae68d0d882ebdcc0-c",
      "title": "山西能源监管办构建供电企业供电能力评价体系",
      "url": "https://www.nea.gov.cn/20260602/3b7979c3c6644484ae68d0d882ebdcc0/c.html",
      "summary": "",
      "publishedAt": "2026-06-02",
      "source": "nea.gov.cn"
    },
    {
      "id": "nea-20260602-1ba59b09bf5a4b99b61a7ba3eeb2fbbe-c",
      "title": "浙江能源监管办全面部署2026年提升“获得电力”服务水平监管工作",
      "url": "https://www.nea.gov.cn/20260602/1ba59b09bf5a4b99b61a7ba3eeb2fbbe/c.html",
      "summary": "",
      "publishedAt": "2026-06-02",
      "source": "nea.gov.cn"
    },
    {
      "id": "nea-20260602-9e5c5c0d17e34faea27f8797359c39cd-c",
      "title": "江苏能源监管办部署开展2026年电力业务资质许可专项监管",
      "url": "https://www.nea.gov.cn/20260602/9e5c5c0d17e34faea27f8797359c39cd/c.html",
      "summary": "",
      "publishedAt": "2026-06-02",
      "source": "nea.gov.cn"
    },
    {
      "id": "nea-20260602-fd761b3d05c74ce1b5eee6c6b4955059-c",
      "title": "福建能源监管办主动靠前服务 有序做好电力业务许可证延续工作",
      "url": "https://www.nea.gov.cn/20260602/fd761b3d05c74ce1b5eee6c6b4955059/c.html",
      "summary": "",
      "publishedAt": "2026-06-02",
      "source": "nea.gov.cn"
    },
    {
      "id": "nea-20260602-f3bbba176d1f4ea5ab7eacd499d0e51c-c",
      "title": "河南能源监管办赴豫西南督导迎峰度夏电力保供工作",
      "url": "https://www.nea.gov.cn/20260602/f3bbba176d1f4ea5ab7eacd499d0e51c/c.html",
      "summary": "",
      "publishedAt": "2026-06-02",
      "source": "nea.gov.cn",
      "province": "河南"
    },
    {
      "id": "nea-20260602-9b8a137ad5a842eb802b6f41ed30d3e8-c",
      "title": "四川能源监管办从严抓实汛期电力防灾保供工作",
      "url": "https://www.nea.gov.cn/20260602/9b8a137ad5a842eb802b6f41ed30d3e8/c.html",
      "summary": "",
      "publishedAt": "2026-06-02",
      "source": "nea.gov.cn"
    },
    {
      "id": "nea-20260602-e444f35f81e74e6b8b00bc9d3aa8d473-c",
      "title": "云南能源监管办开展供电许可专项排查",
      "url": "https://www.nea.gov.cn/20260602/e444f35f81e74e6b8b00bc9d3aa8d473/c.html",
      "summary": "",
      "publishedAt": "2026-06-02",
      "source": "nea.gov.cn"
    },
    {
      "id": "xinhua-ee98e1635cca",
      "title": "中国石化高性能碳纤维技术研发获重大突破",
      "url": "https://www.xinhuanet.com/energy/20260602/ee98e1635cca4517b56c861e60fe2d30/c.html",
      "summary": "",
      "publishedAt": "2026-06-02",
      "source": "xinhuanet.com"
    },
    {
      "id": "china5e-1204439",
      "title": "华测ADCP：重塑水文流量测验高效新范式",
      "url": "https://www.china5e.com/news/news-1204439-1.html",
      "summary": "",
      "publishedAt": "2026-06-01",
      "source": "china5e.com"
    },
    {
      "id": "cpnn-t20260601_1892045",
      "title": "示范工程全面建成！“超碳一号”第二台机组并网发电",
      "url": "https://www.cpnn.com.cn/news/xwtt/202606/t20260601_1892045.html",
      "summary": "",
      "publishedAt": "2026-06-01",
      "source": "cpnn.com.cn"
    },
    {
      "id": "cpnn-t20260601_1892098",
      "title": "五部门印发 《非化石能源电力消费核算指南（试行）》",
      "url": "https://www.cpnn.com.cn/news/nytt/202606/t20260601_1892098.html",
      "summary": "",
      "publishedAt": "2026-06-01",
      "source": "cpnn.com.cn"
    },
    {
      "id": "cpnn-t20260601_1891966",
      "title": "新能源渗透率连续“破六”！充电桩够吗？保费会降吗？",
      "url": "https://www.cpnn.com.cn/news/xny/202606/t20260601_1891966.html",
      "summary": "",
      "publishedAt": "2026-06-01",
      "source": "cpnn.com.cn"
    },
    {
      "id": "cpnn-t20260601_1892066",
      "title": "国家电网公司组织开展2026年“安全生产月”活动",
      "url": "https://www.cpnn.com.cn/news/nyqy/202606/t20260601_1892066.html",
      "summary": "",
      "publishedAt": "2026-06-01",
      "source": "cpnn.com.cn"
    },
    {
      "id": "cpnn-t20260601_1891883",
      "title": "南方电网公司与中国石油集团签署战略合作协议",
      "url": "https://www.cpnn.com.cn/news/nyqy/202606/t20260601_1891883.html",
      "summary": "",
      "publishedAt": "2026-06-01",
      "source": "cpnn.com.cn"
    },
    {
      "id": "cpnn-t20260601_1891891",
      "title": "内蒙古多家国企联合成立新能源投资合伙企业国金新能",
      "url": "https://www.cpnn.com.cn/news/nyqy/202606/t20260601_1891891.html",
      "summary": "",
      "publishedAt": "2026-06-01",
      "source": "cpnn.com.cn"
    },
    {
      "id": "cpnn-t20260601_1891929",
      "title": "广东成为南方区域首个“小时级”绿电精准匹配与溯源省份",
      "url": "https://www.cpnn.com.cn/news/dfny/202606/t20260601_1891929.html",
      "summary": "",
      "publishedAt": "2026-06-01",
      "source": "cpnn.com.cn"
    },
    {
      "id": "cpnn-t20260601_1891978",
      "title": "西藏: “十五五”清洁能源装机目标6000万千瓦",
      "url": "https://www.cpnn.com.cn/news/dfny/202606/t20260601_1891978.html",
      "summary": "",
      "publishedAt": "2026-06-01",
      "source": "cpnn.com.cn"
    },
    {
      "id": "cpnn-t20260601_1891885",
      "title": "浙江今年通过省间电力现货市场购电量突破50亿千瓦时",
      "url": "https://www.cpnn.com.cn/news/dfny/202606/t20260601_1891885.html",
      "summary": "",
      "publishedAt": "2026-06-01",
      "source": "cpnn.com.cn"
    },
    {
      "id": "cpnn-t20260601_1891906",
      "title": "长江上建起首座“零碳岛”",
      "url": "https://www.cpnn.com.cn/news/dfny/202606/t20260601_1891906.html",
      "summary": "",
      "publishedAt": "2026-06-01",
      "source": "cpnn.com.cn"
    },
    {
      "id": "cpnn-t20260601_1891928",
      "title": "全国首个绿色算力全栈AI平台上线运行",
      "url": "https://www.cpnn.com.cn/news/kj/202606/t20260601_1891928.html",
      "summary": "",
      "publishedAt": "2026-06-01",
      "source": "cpnn.com.cn"
    },
    {
      "id": "cpnn-t20260601_1891959",
      "title": "单壁碳纳米管产能达单台10吨级",
      "url": "https://www.cpnn.com.cn/news/kj/202606/t20260601_1891959.html",
      "summary": "",
      "publishedAt": "2026-06-01",
      "source": "cpnn.com.cn"
    },
    {
      "id": "cpnn-t20260601_1891862",
      "title": "专家：新能源装机规模居全球首位 正从补充能源迈向主体能源",
      "url": "https://www.cpnn.com.cn/news/baogao2023/202606/t20260601_1891862.html",
      "summary": "",
      "publishedAt": "2026-06-01",
      "source": "cpnn.com.cn"
    },
    {
      "id": "cpnn-t20260601_1892024",
      "title": "国网甘肃电力：开展2026年甘肃省迎峰度夏电力负荷管理实战化演练",
      "url": "https://www.cpnn.com.cn/qiye/dianwangPD2023/202606/t20260601_1892024.html",
      "summary": "",
      "publishedAt": "2026-06-01",
      "source": "cpnn.com.cn"
    },
    {
      "id": "cpnn-t20260601_1892043",
      "title": "大唐发电举办企业开放日 传递央企品牌担当",
      "url": "https://www.cpnn.com.cn/qiye/fadianPD2023/202606/t20260601_1892043.html",
      "summary": "",
      "publishedAt": "2026-06-01",
      "source": "cpnn.com.cn"
    },
    {
      "id": "cpnn-t20260601_1892056",
      "title": "大唐韩城第二发电：赴澄城县窑头镇开展党日活动",
      "url": "https://www.cpnn.com.cn/qiye/guanli/202606/t20260601_1892056.html",
      "summary": "",
      "publishedAt": "2026-06-01",
      "source": "cpnn.com.cn"
    },
    {
      "id": "cpnn-t20260601_1892011",
      "title": "内蒙古电力数字研究公司：传承守望相助情 凝聚数智奋进力",
      "url": "https://www.cpnn.com.cn/qiye/guanli/202606/t20260601_1892011.html",
      "summary": "",
      "publishedAt": "2026-06-01",
      "source": "cpnn.com.cn"
    },
    {
      "id": "cpnn-t20260601_1892010",
      "title": "内蒙古电力数字研究公司各党支部联合电力腾飞社区开展主题党日活动",
      "url": "https://www.cpnn.com.cn/qiye/guanli/202606/t20260601_1892010.html",
      "summary": "",
      "publishedAt": "2026-06-01",
      "source": "cpnn.com.cn"
    },
    {
      "id": "cpnn-t20260601_1892023",
      "title": "国网漳县供电：坚守运维一线 筑牢电网安全防线",
      "url": "https://www.cpnn.com.cn/qiye/anquan/202606/t20260601_1892023.html",
      "summary": "",
      "publishedAt": "2026-06-01",
      "source": "cpnn.com.cn"
    },
    {
      "id": "cpnn-t20260601_1892008",
      "title": "国网北碚供电主动调研电力需求助力地方高质量发展",
      "url": "https://www.cpnn.com.cn/qiye/zggdsPD2023/202606/t20260601_1892008.html",
      "summary": "",
      "publishedAt": "2026-06-01",
      "source": "cpnn.com.cn"
    },
    {
      "id": "cpnn-t20260601_1892015",
      "title": "电建核电公司：让青春与“山海”一样美",
      "url": "https://www.cpnn.com.cn/qiye/yingcai/202606/t20260601_1892015.html",
      "summary": "",
      "publishedAt": "2026-06-01",
      "source": "cpnn.com.cn"
    },
    {
      "id": "xinhua-8ca47302c8df",
      "title": "27.1GWh！国内新型储能一季度装机数据发布",
      "url": "https://www.xinhuanet.com/energy/20260601/8ca47302c8df4095a584f4b755000b77/c.html",
      "summary": "",
      "publishedAt": "2026-06-01",
      "source": "xinhuanet.com"
    },
    {
      "id": "xinhua-993dade7a36a",
      "title": "发力补上低碳产业短板",
      "url": "https://www.xinhuanet.com/energy/20260601/993dade7a36a4d939245c50606ba94c6/c.html",
      "summary": "",
      "publishedAt": "2026-06-01",
      "source": "xinhuanet.com"
    },
    {
      "id": "xinhua-69b8bce4aba7",
      "title": "国家能源局：激发能源领域民企创新发展动能",
      "url": "https://www.xinhuanet.com/energy/20260601/69b8bce4aba7456c8086faacce29dbed/c.html",
      "summary": "",
      "publishedAt": "2026-06-01",
      "source": "xinhuanet.com"
    },
    {
      "id": "china5e-1204400",
      "title": "第八届综合能源服务落地实践峰会在南京圆满落幕共绘产业发展新蓝图",
      "url": "https://www.china5e.com/news/news-1204400-1.html",
      "summary": "",
      "publishedAt": "2026-05-31",
      "source": "china5e.com"
    },
    {
      "id": "china5e-1204387",
      "title": "生态环境部印发《海湾清洁指数评价技术方法（试行）》",
      "url": "https://www.china5e.com/news/news-1204387-1.html",
      "summary": "",
      "publishedAt": "2026-05-29",
      "source": "china5e.com"
    },
    {
      "id": "china5e-1204384",
      "title": "生态环境部：今年启动对国家公园和自然公园生态环保成效评估工作",
      "url": "https://www.china5e.com/news/news-1204384-1.html",
      "summary": "",
      "publishedAt": "2026-05-29",
      "source": "china5e.com"
    },
    {
      "id": "cpnn-t20260529_1891474",
      "title": "全球最大储能实证平台在厦门启动",
      "url": "https://www.cpnn.com.cn/news/xny/202605/t20260529_1891474.html",
      "summary": "",
      "publishedAt": "2026-05-29",
      "source": "cpnn.com.cn"
    },
    {
      "id": "cpnn-t20260529_1891462",
      "title": "培育节能降碳新生态",
      "url": "https://www.cpnn.com.cn/news/ydylnyhz/202605/t20260529_1891462.html",
      "summary": "",
      "publishedAt": "2026-05-29",
      "source": "cpnn.com.cn"
    },
    {
      "id": "cpnn-t20260529_1891618",
      "title": "中能财经 | 资金用脚投票，电力哪些赛道浮...",
      "url": "https://www.cpnn.com.cn/news/zngc/202605/t20260529_1891618.html",
      "summary": "",
      "publishedAt": "2026-05-29",
      "source": "cpnn.com.cn"
    },
    {
      "id": "cpnn-t20260529_1891699",
      "title": "切换储能！绿发电力拟变更募资用途",
      "url": "https://www.cpnn.com.cn/news/nyqy/202605/t20260529_1891699.html",
      "summary": "",
      "publishedAt": "2026-05-29",
      "source": "cpnn.com.cn"
    },
    {
      "id": "cpnn-t20260529_1891543",
      "title": "国网漳县供电：化解六级电网风险 守护万家灯火无忧",
      "url": "https://www.cpnn.com.cn/qiye/anquan/202605/t20260529_1891543.html",
      "summary": "",
      "publishedAt": "2026-05-29",
      "source": "cpnn.com.cn"
    },
    {
      "id": "cpnn-t20260529_1891578",
      "title": "吉林长春召开新型储能微电网与国防应用研讨会",
      "url": "https://www.cpnn.com.cn/qiye/jishu2023/202605/t20260529_1891578.html",
      "summary": "",
      "publishedAt": "2026-05-29",
      "source": "cpnn.com.cn"
    },
    {
      "id": "nea-20260529-a4df1c37d41c4d768fe9443c85ca9d4d-c",
      "title": "新型电网 更强更绿更智能",
      "url": "https://www.nea.gov.cn/20260529/a4df1c37d41c4d768fe9443c85ca9d4d/c.html",
      "summary": "",
      "publishedAt": "2026-05-29",
      "source": "nea.gov.cn"
    },
    {
      "id": "nea-20260529-06bfffb1c5054f2b8663dbf9185c9892-c",
      "title": "我国首个专业货运枢纽机场光伏发电突破1亿千瓦时",
      "url": "https://www.nea.gov.cn/20260529/06bfffb1c5054f2b8663dbf9185c9892/c.html",
      "summary": "",
      "publishedAt": "2026-05-29",
      "source": "nea.gov.cn"
    },
    {
      "id": "china5e-1204268",
      "title": "我国首个专业货运枢纽机场光伏发电突破1亿千瓦时",
      "url": "https://www.china5e.com/news/news-1204268-1.html",
      "summary": "",
      "publishedAt": "2026-05-28",
      "source": "china5e.com"
    },
    {
      "id": "china5e-1204313",
      "title": "赋能绿色转型，共筑低碳未来 --纺织行业气候专才计划2026年第一期项目圆满召开",
      "url": "https://www.china5e.com/news/news-1204313-1.html",
      "summary": "",
      "publishedAt": "2026-05-28",
      "source": "china5e.com"
    },
    {
      "id": "china5e-1204318",
      "title": "“控碳网”编织起内蒙古经济转型新动能——内蒙古碳中和产业协会打造全区绿色低碳智慧平台",
      "url": "https://www.china5e.com/news/news-1204318-1.html",
      "summary": "",
      "publishedAt": "2026-05-28",
      "source": "china5e.com"
    },
    {
      "id": "cpnn-t20260528_1891250",
      "title": "2026年1-4月全国电力市场交易电量同比增长25.6%",
      "url": "https://www.cpnn.com.cn/news/xwtt/202605/t20260528_1891250.html",
      "summary": "",
      "publishedAt": "2026-05-28",
      "source": "cpnn.com.cn"
    },
    {
      "id": "nea-20260528-d2fed98964fc4b018e2ab129df4cbf8e-c",
      "title": "2026年1-4月全国电力市场交易电量同比增长25.6%",
      "url": "https://www.nea.gov.cn/20260528/d2fed98964fc4b018e2ab129df4cbf8e/c.html",
      "summary": "",
      "publishedAt": "2026-05-28",
      "source": "nea.gov.cn"
    },
    {
      "id": "china5e-1204249",
      "title": "聚苯乙烯马来酸酐（SMA）与MPEG聚醚梳形改性分散剂的",
      "url": "https://www.china5e.com/news/news-1204249-1.html",
      "summary": "",
      "publishedAt": "2026-05-27",
      "source": "china5e.com"
    },
    {
      "id": "cpnn-t20260527_1890968",
      "title": "大唐陕西新能源：以风光之约 迎春花秋实",
      "url": "https://www.cpnn.com.cn/qiye/yingcai/202605/t20260527_1890968.html",
      "summary": "",
      "publishedAt": "2026-05-27",
      "source": "cpnn.com.cn"
    },
    {
      "id": "nea-20260527-e1586e72e3124fb6a96b033567ce5713-c",
      "title": "国家能源局主要负责同志赴广东省深圳市调研能源强国建设工作",
      "url": "https://www.nea.gov.cn/20260527/e1586e72e3124fb6a96b033567ce5713/c.html",
      "summary": "",
      "publishedAt": "2026-05-27",
      "source": "nea.gov.cn"
    },
    {
      "id": "nea-20260527-ad612fe227504da0bdaafe63f7433b9f-c",
      "title": "国家能源局召开全国“人工智能+”能源现场推进会",
      "url": "https://www.nea.gov.cn/20260527/ad612fe227504da0bdaafe63f7433b9f/c.html",
      "summary": "",
      "publishedAt": "2026-05-27",
      "source": "nea.gov.cn"
    },
    {
      "id": "nea-20260527-a9cf945b4e014e918719c3a99889d76f-c",
      "title": "国家能源局召开民营企业座谈会",
      "url": "https://www.nea.gov.cn/20260527/a9cf945b4e014e918719c3a99889d76f/c.html",
      "summary": "",
      "publishedAt": "2026-05-27",
      "source": "nea.gov.cn"
    },
    {
      "id": "china5e-1204204",
      "title": "2026碳足迹认证企业推荐",
      "url": "https://www.china5e.com/news/news-1204204-1.html",
      "summary": "",
      "publishedAt": "2026-05-26",
      "source": "china5e.com"
    },
    {
      "id": "cpnn-t20260526_1890664",
      "title": "国家能源局召开民营企业座谈会",
      "url": "https://www.cpnn.com.cn/news/xwtt/202605/t20260526_1890664.html",
      "summary": "",
      "publishedAt": "2026-05-26",
      "source": "cpnn.com.cn"
    },
    {
      "id": "cpnn-t20260526_1890595",
      "title": "2.59亿千瓦！南方电网电力负荷创新高",
      "url": "https://www.cpnn.com.cn/news/xwtt/202605/t20260526_1890595.html",
      "summary": "",
      "publishedAt": "2026-05-26",
      "source": "cpnn.com.cn"
    },
    {
      "id": "cpnn-t20260526_1890481",
      "title": "国网甘肃电力：全力攻坚“供电服务一张网”建设",
      "url": "https://www.cpnn.com.cn/qiye/dianwangPD2023/202605/t20260526_1890481.html",
      "summary": "",
      "publishedAt": "2026-05-26",
      "source": "cpnn.com.cn"
    },
    {
      "id": "cpnn-t20260526_1890610",
      "title": "大唐巩义发电公司尤祥光：十年磨一剑 今朝试锋芒",
      "url": "https://www.cpnn.com.cn/qiye/yingcai/202605/t20260526_1890610.html",
      "summary": "",
      "publishedAt": "2026-05-26",
      "source": "cpnn.com.cn"
    },
    {
      "id": "cpnn-t20260526_1890609",
      "title": "大唐巩义发电薛定国：煤海攻坚降本记",
      "url": "https://www.cpnn.com.cn/qiye/yingcai/202605/t20260526_1890609.html",
      "summary": "",
      "publishedAt": "2026-05-26",
      "source": "cpnn.com.cn"
    },
    {
      "id": "china5e-1204124",
      "title": "超级物种·能亮站「艺墅家」：以光筑墅，智启墅居绿电新境",
      "url": "https://www.china5e.com/news/news-1204124-1.html",
      "summary": "",
      "publishedAt": "2026-05-25",
      "source": "china5e.com"
    },
    {
      "id": "nea-20260525-00667d31b6614d8cb1c9ce019fb0946b-c",
      "title": "国家能源局召开青年理论学习小组组长座谈会",
      "url": "https://www.nea.gov.cn/20260525/00667d31b6614d8cb1c9ce019fb0946b/c.html",
      "summary": "",
      "publishedAt": "2026-05-25",
      "source": "nea.gov.cn"
    },
    {
      "id": "nea-20260525-c509435a0f09497cb3d2ca361fa262de-c",
      "title": "国家能源局发布2026年1-4月份全国电力统计数据",
      "url": "https://www.nea.gov.cn/20260525/c509435a0f09497cb3d2ca361fa262de/c.html",
      "summary": "",
      "publishedAt": "2026-05-25",
      "source": "nea.gov.cn"
    },
    {
      "id": "china5e-1204046",
      "title": "北京绿电市场化交易规模首次超过火电",
      "url": "https://www.china5e.com/news/news-1204046-1.html",
      "summary": "",
      "publishedAt": "2026-05-22",
      "source": "china5e.com"
    },
    {
      "id": "cpnn-t20260522_1889681",
      "title": "节能风电总经理任职",
      "url": "https://www.cpnn.com.cn/news/renshi2023/202605/t20260522_1889681.html",
      "summary": "",
      "publishedAt": "2026-05-22",
      "source": "cpnn.com.cn"
    },
    {
      "id": "cpnn-t20260522_1889835",
      "title": "国家电投集团江西核电（天红科技）招聘公告",
      "url": "https://www.cpnn.com.cn/news/zhaopinxinxi2023/202605/t20260522_1889835.html",
      "summary": "",
      "publishedAt": "2026-05-22",
      "source": "cpnn.com.cn",
      "province": "江西"
    },
    {
      "id": "cpnn-t20260522_1889652",
      "title": "大唐环境新能源设计高层次专业人才公开招聘",
      "url": "https://www.cpnn.com.cn/news/zhaopinxinxi2023/202605/t20260522_1889652.html",
      "summary": "",
      "publishedAt": "2026-05-22",
      "source": "cpnn.com.cn"
    },
    {
      "id": "nea-20260522-0eb55ff1f81542e18a50d5ce8a3fd61e-c",
      "title": "协同布局，能源强国建设扎实推进（“十五五”开好局起好步）",
      "url": "https://www.nea.gov.cn/20260522/0eb55ff1f81542e18a50d5ce8a3fd61e/c.html",
      "summary": "",
      "publishedAt": "2026-05-22",
      "source": "nea.gov.cn"
    },
    {
      "id": "nea-20260522-02e4504688c04c1884f803ff04c0fa7c-c",
      "title": "下好电力市场建设“一盘棋”",
      "url": "https://www.nea.gov.cn/20260522/02e4504688c04c1884f803ff04c0fa7c/c.html",
      "summary": "",
      "publishedAt": "2026-05-22",
      "source": "nea.gov.cn"
    },
    {
      "id": "nea-20260522-766f6734da5e4ff8ad0eabdbf154afcc-c",
      "title": "针对不同技术路线划定质量监督“硬杠杠”——让新型储能电站“建得好、用得稳”",
      "url": "https://www.nea.gov.cn/20260522/766f6734da5e4ff8ad0eabdbf154afcc/c.html",
      "summary": "",
      "publishedAt": "2026-05-22",
      "source": "nea.gov.cn"
    },
    {
      "id": "nea-20260520-99326d59f0404dc49577f0bfc7f3d930-c",
      "title": "国家能源局有关负责同志就《关于有序推动多用户绿电直连发展有关事项的通知》答记者问",
      "url": "https://www.nea.gov.cn/20260520/99326d59f0404dc49577f0bfc7f3d930/c.html",
      "summary": "",
      "publishedAt": "2026-05-20",
      "source": "nea.gov.cn"
    },
    {
      "id": "nea-20260520-a842d14ccabc461292fa190e6618bb60-c",
      "title": "国家能源局有关负责同志就《核电厂退役准备管理暂行办法》答记者问",
      "url": "https://www.nea.gov.cn/20260520/a842d14ccabc461292fa190e6618bb60/c.html",
      "summary": "",
      "publishedAt": "2026-05-20",
      "source": "nea.gov.cn"
    },
    {
      "id": "china5e-1203838",
      "title": "红河元阳分布式光伏铺就“阳光致富路”",
      "url": "https://www.china5e.com/news/news-1203838-1.html",
      "summary": "",
      "publishedAt": "2026-05-19",
      "source": "china5e.com"
    },
    {
      "id": "china5e-1203867",
      "title": "河北省四地区市场化绿电首次进京",
      "url": "https://www.china5e.com/news/news-1203867-1.html",
      "summary": "",
      "publishedAt": "2026-05-19",
      "source": "china5e.com"
    },
    {
      "id": "nea-20260519-6008bb88dc0649e5b5530fd6ad0b117a-c",
      "title": "2026年一季度光伏发电建设情况",
      "url": "https://www.nea.gov.cn/20260519/6008bb88dc0649e5b5530fd6ad0b117a/c.html",
      "summary": "",
      "publishedAt": "2026-05-19",
      "source": "nea.gov.cn"
    },
    {
      "id": "nea-20260515-76a82a7375a942e2ab748b36cf7cc14b-c",
      "title": "中国绿色电力证书发展报告（2025）",
      "url": "https://www.nea.gov.cn/20260515/76a82a7375a942e2ab748b36cf7cc14b/c.html",
      "summary": "",
      "publishedAt": "2026-05-15",
      "source": "nea.gov.cn"
    },
    {
      "id": "nea-20260514-909214e27a08460faa0e1e674e8f41cf-c",
      "title": "《新型储能电站建设工程质量监督大纲》政策解读",
      "url": "https://www.nea.gov.cn/20260514/909214e27a08460faa0e1e674e8f41cf/c.html",
      "summary": "",
      "publishedAt": "2026-05-14",
      "source": "nea.gov.cn"
    },
    {
      "id": "nea-20260513-a38f9ff036f145a7bcfb6724e9f8d89e-c",
      "title": "国家能源局公告 2026年 第1号",
      "url": "https://www.nea.gov.cn/20260513/a38f9ff036f145a7bcfb6724e9f8d89e/c.html",
      "summary": "",
      "publishedAt": "2026-05-13",
      "source": "nea.gov.cn"
    },
    {
      "id": "nea-20260509-45e5721670704d4e8555d2212211db45-c",
      "title": "国家能源局联合相关部门促进人工智能与能源双向赋能",
      "url": "https://www.nea.gov.cn/20260509/45e5721670704d4e8555d2212211db45/c.html",
      "summary": "",
      "publishedAt": "2026-05-09",
      "source": "nea.gov.cn"
    },
    {
      "id": "nea-20260429-77ddd08c10304befa9d8482b87d709a7-c",
      "title": "中乌能源合作分委会第八次会议成功举行",
      "url": "https://www.nea.gov.cn/20260429/77ddd08c10304befa9d8482b87d709a7/c.html",
      "summary": "",
      "publishedAt": "2026-04-29",
      "source": "nea.gov.cn"
    },
    {
      "id": "cpnn-t20260428_1884295",
      "title": "汛期将至，4月23日，大唐岩滩水力发电有限责任公司组织开展超标准洪水防洪调度应急预案实战化、全面性演练，以实景实训锤炼公司应急队伍。",
      "url": "https://www.cpnn.com.cn/qiye/anquan/202604/t20260428_1884295.html",
      "summary": "",
      "publishedAt": "2026-04-28",
      "source": "cpnn.com.cn"
    },
    {
      "id": "nea-20260428-580e910ff2344b59bac10f9f10fb580f-c",
      "title": "能源行业核电标准化技术委员会召开年度会议",
      "url": "https://www.nea.gov.cn/20260428/580e910ff2344b59bac10f9f10fb580f/c.html",
      "summary": "",
      "publishedAt": "2026-04-28",
      "source": "nea.gov.cn"
    },
    {
      "id": "nea-20260424-05f5cfe1ff89490495ae1db8fb1c4932-c",
      "title": "国家能源局召开长三角电力市场建设专题推进会",
      "url": "https://www.nea.gov.cn/20260424/05f5cfe1ff89490495ae1db8fb1c4932/c.html",
      "summary": "",
      "publishedAt": "2026-04-24",
      "source": "nea.gov.cn"
    },
    {
      "id": "nea-20260423-ba4fc99321fa4da19624eeeb2d5e4135-c",
      "title": "关于2026年3月全国新增建档立卡新能源发电（不含户用光伏）项目情况的公告",
      "url": "https://www.nea.gov.cn/20260423/ba4fc99321fa4da19624eeeb2d5e4135/c.html",
      "summary": "",
      "publishedAt": "2026-04-23",
      "source": "nea.gov.cn"
    },
    {
      "id": "nea-20260416-a0df479d9c42427fbc9d8c86ddf6537f-c",
      "title": "国家能源局在全国部署开展供电质量提升专项行动",
      "url": "https://www.nea.gov.cn/20260416/a0df479d9c42427fbc9d8c86ddf6537f/c.html",
      "summary": "",
      "publishedAt": "2026-04-16",
      "source": "nea.gov.cn"
    },
    {
      "id": "nea-20260416-3c51e47b101e4f2781e04be63c2e90d6-c",
      "title": "股份经济合作社属于《关于深化提升“获得电力”服务水平 全面打造现代化用电营商环境的意见》（发改能源规〔2025〕624号）中提到的民营经济组织吗？",
      "url": "https://www.nea.gov.cn/20260416/3c51e47b101e4f2781e04be63c2e90d6/c.html",
      "summary": "",
      "publishedAt": "2026-04-16",
      "source": "nea.gov.cn"
    },
    {
      "id": "cpnn-t20260414_1880730",
      "title": "大唐陈村水力发电公司推动学习教育走深见效",
      "url": "https://www.cpnn.com.cn/qiye/guanli/202604/t20260414_1880730.html",
      "summary": "",
      "publishedAt": "2026-04-14",
      "source": "cpnn.com.cn"
    },
    {
      "id": "cpnn-t20260410_1880238",
      "title": "塔山发电公司曹莎：锐意进取绽芳华",
      "url": "https://www.cpnn.com.cn/qiye/yingcai/202604/t20260410_1880238.html",
      "summary": "",
      "publishedAt": "2026-04-10",
      "source": "cpnn.com.cn"
    },
    {
      "id": "nea-20260407-8318743a08f04274824087ea62cf6728-c",
      "title": "《关于提升新能源和新型并网主体涉网安全能力服务新型电力系统高质量发展的通知》中涉网参数检测单位资质的问题",
      "url": "https://www.nea.gov.cn/20260407/8318743a08f04274824087ea62cf6728/c.html",
      "summary": "",
      "publishedAt": "2026-04-07",
      "source": "nea.gov.cn"
    },
    {
      "id": "nea-20260331-203488b39d454d76a3c9f04fce97eaca-c",
      "title": "国家能源局湖南监管办党组关于巡视“回头看”整改进展情况的通报",
      "url": "https://www.nea.gov.cn/20260331/203488b39d454d76a3c9f04fce97eaca/c.html",
      "summary": "",
      "publishedAt": "2026-03-31",
      "source": "nea.gov.cn",
      "province": "湖南"
    },
    {
      "id": "nea-20260331-e6fd0fd4dcc04a668b37cf63f819e0b6-c",
      "title": "国家能源局华东监管局党组关于巡视“回头看”整改进展情况的通报",
      "url": "https://www.nea.gov.cn/20260331/e6fd0fd4dcc04a668b37cf63f819e0b6/c.html",
      "summary": "",
      "publishedAt": "2026-03-31",
      "source": "nea.gov.cn"
    },
    {
      "id": "nea-20260331-1bf84fffaa9945c29cef4c144a04d8db-c",
      "title": "国家能源局华中监管局党组关于局党组第三轮巡视整改进展情况的通报",
      "url": "https://www.nea.gov.cn/20260331/1bf84fffaa9945c29cef4c144a04d8db/c.html",
      "summary": "",
      "publishedAt": "2026-03-31",
      "source": "nea.gov.cn",
      "province": "华中"
    },
    {
      "id": "nea-20260331-880468e48ffb4d0083a99ad154b0d075-c",
      "title": "国家能源局机关服务中心党支部关于局党组第三轮巡视整改进展情况的通报",
      "url": "https://www.nea.gov.cn/20260331/880468e48ffb4d0083a99ad154b0d075/c.html",
      "summary": "",
      "publishedAt": "2026-03-31",
      "source": "nea.gov.cn"
    },
    {
      "id": "nea-20260331-b279a574b5d94d3e84f4b68c08810f19-c",
      "title": "中国能源传媒集团有限公司党委关于国家能源局党组第三轮巡视整改进展情况的通报",
      "url": "https://www.nea.gov.cn/20260331/b279a574b5d94d3e84f4b68c08810f19/c.html",
      "summary": "",
      "publishedAt": "2026-03-31",
      "source": "nea.gov.cn"
    },
    {
      "id": "nea-20260331-f5da50c4e7384c6caadd1d72fb2a8d62-c",
      "title": "国家能源局电力业务资质管理中心党支部关于局党组第三轮巡视整改进展情况的通报",
      "url": "https://www.nea.gov.cn/20260331/f5da50c4e7384c6caadd1d72fb2a8d62/c.html",
      "summary": "",
      "publishedAt": "2026-03-31",
      "source": "nea.gov.cn"
    },
    {
      "id": "nea-20260123-8cc1c720812647ffaecf009dc8e9aa99-c",
      "title": "《电力业务许可证延续及注销管理办法》政策解读",
      "url": "https://www.nea.gov.cn/20260123/8cc1c720812647ffaecf009dc8e9aa99/c.html",
      "summary": "",
      "publishedAt": "2026-01-23",
      "source": "nea.gov.cn"
    },
    {
      "id": "nea-20260107-63c64abd894644fe8668eb2d83064419-c",
      "title": "《能源行业公共信用信息管理办法》政策解读",
      "url": "https://www.nea.gov.cn/20260107/63c64abd894644fe8668eb2d83064419/c.html",
      "summary": "",
      "publishedAt": "2026-01-07",
      "source": "nea.gov.cn"
    },
    {
      "id": "nea-20260107-3f7a58d6f6a54b1a96b29e0f50cbd04d-c",
      "title": "《国家能源局关于印发〈可再生能源绿色电力证书管理实施细则（试行）〉的通知》解读",
      "url": "https://www.nea.gov.cn/20260107/3f7a58d6f6a54b1a96b29e0f50cbd04d/c.html",
      "summary": "",
      "publishedAt": "2026-01-07",
      "source": "nea.gov.cn"
    },
    {
      "id": "nea-20251231-c4a95213421640228212a0f73beb244f-c",
      "title": "国家能源局有关负责同志就《关于促进电网高质量发展的指导意见》答记者问",
      "url": "https://www.nea.gov.cn/20251231/c4a95213421640228212a0f73beb244f/c.html",
      "summary": "",
      "publishedAt": "2025-12-31",
      "source": "nea.gov.cn"
    },
    {
      "id": "nea-20251223-967388be198f422cb92b86a81e7e5ef9-c",
      "title": "国家能源局有关负责同志就《关于促进光热发电规模化发展的若干意见》答记者问",
      "url": "https://www.nea.gov.cn/20251223/967388be198f422cb92b86a81e7e5ef9/c.html",
      "summary": "",
      "publishedAt": "2025-12-23",
      "source": "nea.gov.cn"
    },
    {
      "id": "nea-20251212-dfceb7a814f942838889a87a2918615d-c",
      "title": "国家能源局有关负责同志就《能源行业数据安全管理办法（试行）》答记者问",
      "url": "https://www.nea.gov.cn/20251212/dfceb7a814f942838889a87a2918615d/c.html",
      "summary": "",
      "publishedAt": "2025-12-12",
      "source": "nea.gov.cn"
    },
    {
      "id": "nea-20250422-1a5f2975d3fc4d35a3a10cb90ae7642c-c",
      "title": "2024年分布式光伏备案接网推进情况监管典型案例",
      "url": "https://www.nea.gov.cn/20250422/1a5f2975d3fc4d35a3a10cb90ae7642c/c.html",
      "summary": "",
      "publishedAt": "2025-04-22",
      "source": "nea.gov.cn"
    },
    {
      "id": "nea-20250121-984ec5af3d5a4c8588d48c6a423705cf-c",
      "title": "中丹绿色电力合作项目",
      "url": "https://www.nea.gov.cn/20250121/984ec5af3d5a4c8588d48c6a423705cf/c.html",
      "summary": "",
      "publishedAt": "2025-01-21",
      "source": "nea.gov.cn"
    },
    {
      "id": "nea-20241220-5f6802b47144464a82739b3e4bf6dbee-c",
      "title": "电力安全生产监管典型执法案例（32—34）",
      "url": "https://www.nea.gov.cn/20241220/5f6802b47144464a82739b3e4bf6dbee/c.html",
      "summary": "",
      "publishedAt": "2024-12-20",
      "source": "nea.gov.cn"
    },
    {
      "id": "cpnn-t20220811_1541876",
      "title": "中国电力话语体系课题结题评审会在国网高培...",
      "url": "https://www.cpnn.com.cn/news/xwtopb/202208/t20220811_1541876.html",
      "summary": "",
      "publishedAt": "2022-08-11",
      "source": "cpnn.com.cn"
    },
    {
      "id": "cpnn-t20220715_1533884",
      "title": "国家电网公司召开2022年年中工作会议",
      "url": "https://www.cpnn.com.cn/news/nytt/202207/t20220715_1533884.html",
      "summary": "",
      "publishedAt": "2022-07-15",
      "source": "cpnn.com.cn"
    },
    {
      "id": "cpnn-t20220714_1533519",
      "title": "国家能源局党组部署开展第八轮巡视工作",
      "url": "https://www.cpnn.com.cn/news/nytt/202207/t20220714_1533519.html",
      "summary": "",
      "publishedAt": "2022-07-14",
      "source": "cpnn.com.cn"
    },
    {
      "id": "china5e-1204508",
      "title": "供需角力，6月煤价怎么走?",
      "url": "https://www.china5e.com/news/news-1204508-1.html",
      "summary": "",
      "publishedAt": null,
      "source": "china5e.com"
    },
    {
      "id": "china5e-1204483",
      "title": "煤炭行业周报：煤炭供给弹性约束已显 煤炭价格向上",
      "url": "https://www.china5e.com/news/news-1204483-1.html",
      "summary": "",
      "publishedAt": null,
      "source": "china5e.com"
    },
    {
      "id": "china5e-1204488",
      "title": "虚拟电厂首次参与东北区域省间中长期滚动撮合交易",
      "url": "https://www.china5e.com/news/news-1204488-1.html",
      "summary": "",
      "publishedAt": null,
      "source": "china5e.com"
    },
    {
      "id": "china5e-1204473",
      "title": "5部门印发指南非化石能源电力消费核算有了统一“标尺”",
      "url": "https://www.china5e.com/news/news-1204473-1.html",
      "summary": "",
      "publishedAt": null,
      "source": "china5e.com"
    },
    {
      "id": "china5e-1204504",
      "title": "中煤永城50MW源网荷储一体化项目获核准",
      "url": "https://www.china5e.com/news/news-1204504-1.html",
      "summary": "",
      "publishedAt": null,
      "source": "china5e.com"
    },
    {
      "id": "china5e-1204501",
      "title": "巨头抢滩AIDC储能：阳光电源目标价212元，宁德时代野心直指算电协同全链",
      "url": "https://www.china5e.com/news/news-1204501-1.html",
      "summary": "",
      "publishedAt": null,
      "source": "china5e.com"
    },
    {
      "id": "china5e-1204498",
      "title": "信实工业HJT光伏组件正式投产!",
      "url": "https://www.china5e.com/news/news-1204498-1.html",
      "summary": "",
      "publishedAt": null,
      "source": "china5e.com"
    },
    {
      "id": "china5e-1204497",
      "title": "张家口首个高速隧道独立构网微电网项目并网发电",
      "url": "https://www.china5e.com/news/news-1204497-1.html",
      "summary": "",
      "publishedAt": null,
      "source": "china5e.com"
    },
    {
      "id": "china5e-1204465",
      "title": "智博会观察：国产数智化方案如何重塑油气行业新标准",
      "url": "https://www.china5e.com/news/news-1204465-1.html",
      "summary": "",
      "publishedAt": null,
      "source": "china5e.com"
    },
    {
      "id": "china5e-1204509",
      "title": "独家 | 4月全国动力煤分省供应量解析",
      "url": "https://www.china5e.com/news/news-1204509-1.html",
      "summary": "",
      "publishedAt": null,
      "source": "china5e.com"
    },
    {
      "id": "china5e-1204507",
      "title": "动力煤挺价情绪较强;焦炭迎来第五轮提涨;焦煤供应紧张需求较强!",
      "url": "https://www.china5e.com/news/news-1204507-1.html",
      "summary": "",
      "publishedAt": null,
      "source": "china5e.com"
    }
  ],
  "copper": {
    "mean_price": "105,960 元/吨",
    "change": "+940 元/吨 ↑",
    "price_range": "105,940-105,980 元/吨",
    "brand": "贵冶、江铜、鲁方等",
    "date": "2026-06-02",
    "raw": {
      "low": "105940",
      "high": "105980",
      "mean": "105960",
      "change": "↑940",
      "unit": "元/吨"
    }
  },
  "stats": {
    "totalArticles": 187,
    "bySource": {
      "china5e.com": 51,
      "chinapower.org.cn": 4,
      "cpnn.com.cn": 75,
      "nea.gov.cn": 53,
      "xinhuanet.com": 4
    },
    "byProvince": {
      "湖北": 1,
      "安徽": 2,
      "华中": 2,
      "河南": 1,
      "江西": 1,
      "湖南": 1
    }
  },
  "errors": [
    {
      "source": "bjx.com.cn",
      "errors": [
        "WAF bypassed but parser found 0 articles. The homepage HTML structure may have changed — inspect the HTML."
      ]
    },
    {
      "source": "iesplaza.com",
      "errors": [
        "ConnectionError: ('Connection aborted.', RemoteDisconnected('Remote end closed connection without response'))"
      ]
    },
    {
      "source": "ne21.com",
      "errors": [
        "JS redirect challenge not resolved after Playwright wait"
      ]
    }
  ]
}