{
  "source": "cpnn.com.cn",
  "sourceName": "电网头条（中国能源传媒集团）",
  "generatedAt": "2026-05-27T23:21:54+00:00",
  "lookbackHours": 48,
  "articles": [
    {
      "id": "cpnn-t20260527_1891037",
      "title": "国家能源局主要负责同志赴广东省深圳市调研能源强国建设工作",
      "url": "https://www.cpnn.com.cn/news/nytt/202605/t20260527_1891037.html",
      "summary": "",
      "publishedAt": "2026-05-27",
      "source": "cpnn.com.cn"
    },
    {
      "id": "cpnn-t20260527_1890738",
      "title": "国家能源局公开征求意见",
      "url": "https://www.cpnn.com.cn/news/nytt/202605/t20260527_1890738.html",
      "summary": "",
      "publishedAt": "2026-05-27",
      "source": "cpnn.com.cn"
    },
    {
      "id": "cpnn-t20260527_1890695",
      "title": "国家能源局综合司发布关于发布“人工智能+”能源高价值场景清单和组织开展试点申报工作的通知",
      "url": "https://www.cpnn.com.cn/news/nytt/202605/t20260527_1890695.html",
      "summary": "",
      "publishedAt": "2026-05-27",
      "source": "cpnn.com.cn"
    },
    {
      "id": "cpnn-t20260527_1891048",
      "title": "同一道山梁下 同心织网越山海——国家电网公司对口支援新罗区纪实",
      "url": "https://www.cpnn.com.cn/news/hy/202605/t20260527_1891048.html",
      "summary": "",
      "publishedAt": "2026-05-27",
      "source": "cpnn.com.cn"
    },
    {
      "id": "cpnn-t20260527_1890746",
      "title": "华北能源监管局主要负责同志赴天津开展能源监管调研",
      "url": "https://www.cpnn.com.cn/news/nyjg/202605/t20260527_1890746.html",
      "summary": "",
      "publishedAt": "2026-05-27",
      "source": "cpnn.com.cn"
    },
    {
      "id": "cpnn-t20260527_1890745",
      "title": "华东能源监管局调研电力应急体系建设情况",
      "url": "https://www.cpnn.com.cn/news/nyjg/202605/t20260527_1890745.html",
      "summary": "",
      "publishedAt": "2026-05-27",
      "source": "cpnn.com.cn"
    },
    {
      "id": "cpnn-t20260527_1890715",
      "title": "安全巡查进电站 守护能源生产平安",
      "url": "https://www.cpnn.com.cn/news/dianli2023/202605/t20260527_1890715.html",
      "summary": "",
      "publishedAt": "2026-05-27",
      "source": "cpnn.com.cn"
    },
    {
      "id": "cpnn-t20260527_1890844",
      "title": "氢能商业化步伐提速",
      "url": "https://www.cpnn.com.cn/news/xny/202605/t20260527_1890844.html",
      "summary": "",
      "publishedAt": "2026-05-27",
      "source": "cpnn.com.cn"
    },
    {
      "id": "cpnn-t20260527_1890919",
      "title": "中能观察 | AI+能源 谁先拿到入场券？",
      "url": "https://www.cpnn.com.cn/news/zngc/202605/t20260527_1890919.html",
      "summary": "",
      "publishedAt": "2026-05-27",
      "source": "cpnn.com.cn"
    },
    {
      "id": "cpnn-t20260527_1890846",
      "title": "探访重庆永川山洪灾后：电力正抢修 村民忙清淤 恢复工作有序推进",
      "url": "https://www.cpnn.com.cn/news/dfny/202605/t20260527_1890846.html",
      "summary": "",
      "publishedAt": "2026-05-27",
      "source": "cpnn.com.cn"
    },
    {
      "id": "cpnn-t20260527_1890858",
      "title": "华能绿电护航2026世界智能产业博览会",
      "url": "https://www.cpnn.com.cn/news/kj/202605/t20260527_1890858.html",
      "summary": "",
      "publishedAt": "2026-05-27",
      "source": "cpnn.com.cn"
    },
    {
      "id": "cpnn-t20260527_1890857",
      "title": "海上风电是怎么跨过大海来到我家的？",
      "url": "https://www.cpnn.com.cn/news/kj/202605/t20260527_1890857.html",
      "summary": "",
      "publishedAt": "2026-05-27",
      "source": "cpnn.com.cn"
    },
    {
      "id": "cpnn-t20260527_1891056",
      "title": "解读︱从“保障电能供应”到“提升电能品质”，深刻拓展电力保供内涵",
      "url": "https://www.cpnn.com.cn/news/baogao2023/202605/t20260527_1891056.html",
      "summary": "",
      "publishedAt": "2026-05-27",
      "source": "cpnn.com.cn"
    },
    {
      "id": "cpnn-t20260527_1891047",
      "title": "绿电直连走向多用户 就近消纳迈入新阶段",
      "url": "https://www.cpnn.com.cn/news/baogao2023/202605/t20260527_1891047.html",
      "summary": "",
      "publishedAt": "2026-05-27",
      "source": "cpnn.com.cn"
    },
    {
      "id": "cpnn-t20260527_1890880",
      "title": "国网金昌供电护航新能源并网与电力外送",
      "url": "https://www.cpnn.com.cn/qiye/dianwangPD2023/202605/t20260527_1890880.html",
      "summary": "",
      "publishedAt": "2026-05-27",
      "source": "cpnn.com.cn"
    },
    {
      "id": "cpnn-t20260527_1890959",
      "title": "国家电投盛发发电：夯实机组检修 打好“迎峰度夏”攻坚战",
      "url": "https://www.cpnn.com.cn/qiye/fadianPD2023/202605/t20260527_1890959.html",
      "summary": "",
      "publishedAt": "2026-05-27",
      "source": "cpnn.com.cn"
    },
    {
      "id": "cpnn-t20260527_1890876",
      "title": "兰州倚能电力：廉洁教育润人心 清廉建设在一线",
      "url": "https://www.cpnn.com.cn/qiye/guanli/202605/t20260527_1890876.html",
      "summary": "",
      "publishedAt": "2026-05-27",
      "source": "cpnn.com.cn"
    },
    {
      "id": "cpnn-t20260527_1890966",
      "title": "大唐湖北新能源事业部农光同治拧紧“三夏”安全阀",
      "url": "https://www.cpnn.com.cn/qiye/anquan/202605/t20260527_1890966.html",
      "summary": "",
      "publishedAt": "2026-05-27",
      "source": "cpnn.com.cn"
    },
    {
      "id": "cpnn-t20260527_1890961",
      "title": "循环冷却水电化学智能处理装置于浙江电网首次投运",
      "url": "https://www.cpnn.com.cn/qiye/jishu2023/202605/t20260527_1890961.html",
      "summary": "",
      "publishedAt": "2026-05-27",
      "source": "cpnn.com.cn"
    },
    {
      "id": "cpnn-t20260527_1890982",
      "title": "南方电网依托 openUBMC 打造服务器节能革新标杆",
      "url": "https://www.cpnn.com.cn/qiye/jishu2023/202605/t20260527_1890982.html",
      "summary": "",
      "publishedAt": "2026-05-27",
      "source": "cpnn.com.cn"
    },
    {
      "id": "cpnn-t20260527_1890968",
      "title": "大唐陕西新能源：以风光之约 迎春花秋实",
      "url": "https://www.cpnn.com.cn/qiye/yingcai/202605/t20260527_1890968.html",
      "summary": "",
      "publishedAt": "2026-05-27",
      "source": "cpnn.com.cn"
    },
    {
      "id": "cpnn-t20260527_1890964",
      "title": "中国水利电力物资华南公司获桂冠电力表扬信",
      "url": "https://www.cpnn.com.cn/qiye/rongyu/202605/t20260527_1890964.html",
      "summary": "",
      "publishedAt": "2026-05-27",
      "source": "cpnn.com.cn"
    },
    {
      "id": "cpnn-t20260527_1890883",
      "title": "国网浙江电力科研平台入选工信部重点培育名单",
      "url": "https://www.cpnn.com.cn/qiye/rongyu/202605/t20260527_1890883.html",
      "summary": "",
      "publishedAt": "2026-05-27",
      "source": "cpnn.com.cn"
    },
    {
      "id": "cpnn-t20260526_1890664",
      "title": "国家能源局召开民营企业座谈会",
      "url": "https://www.cpnn.com.cn/news/xwtt/202605/t20260526_1890664.html",
      "summary": "",
      "publishedAt": "2026-05-26",
      "source": "cpnn.com.cn"
    },
    {
      "id": "cpnn-t20260526_1890595",
      "title": "2.59亿千瓦！南方电网电力负荷创新高",
      "url": "https://www.cpnn.com.cn/news/xwtt/202605/t20260526_1890595.html",
      "summary": "",
      "publishedAt": "2026-05-26",
      "source": "cpnn.com.cn"
    },
    {
      "id": "cpnn-t20260526_1890577",
      "title": "“十五五”时期我国新型电网投资预计将超过5万亿元",
      "url": "https://www.cpnn.com.cn/news/xwtt/202605/t20260526_1890577.html",
      "summary": "",
      "publishedAt": "2026-05-26",
      "source": "cpnn.com.cn"
    },
    {
      "id": "cpnn-t20260526_1890663",
      "title": "国家能源局召开全国“人工智能+”能源现场推进会",
      "url": "https://www.cpnn.com.cn/news/nytt/202605/t20260526_1890663.html",
      "summary": "",
      "publishedAt": "2026-05-26",
      "source": "cpnn.com.cn"
    },
    {
      "id": "cpnn-t20260526_1890602",
      "title": "光伏组件两项强制性国家标准正式发布",
      "url": "https://www.cpnn.com.cn/news/hg/202605/t20260526_1890602.html",
      "summary": "",
      "publishedAt": "2026-05-26",
      "source": "cpnn.com.cn"
    },
    {
      "id": "cpnn-t20260526_1890534",
      "title": "1—4月中国新能源汽车出口147万辆，同比增长69%",
      "url": "https://www.cpnn.com.cn/news/xny/202605/t20260526_1890534.html",
      "summary": "",
      "publishedAt": "2026-05-26",
      "source": "cpnn.com.cn"
    },
    {
      "id": "cpnn-t20260526_1890530",
      "title": "瑞银证券：看好清洁能源及相关基础设施投资",
      "url": "https://www.cpnn.com.cn/news/xny/202605/t20260526_1890530.html",
      "summary": "",
      "publishedAt": "2026-05-26",
      "source": "cpnn.com.cn"
    },
    {
      "id": "cpnn-t20260526_1890540",
      "title": "广西：以算电协同探路能源数字融合",
      "url": "https://www.cpnn.com.cn/news/dfny/202605/t20260526_1890540.html",
      "summary": "",
      "publishedAt": "2026-05-26",
      "source": "cpnn.com.cn"
    },
    {
      "id": "cpnn-t20260526_1890541",
      "title": "国网湖北电力以科技手段提升汛期供电可靠性",
      "url": "https://www.cpnn.com.cn/news/kj/202605/t20260526_1890541.html",
      "summary": "",
      "publishedAt": "2026-05-26",
      "source": "cpnn.com.cn"
    },
    {
      "id": "cpnn-t20260526_1890544",
      "title": "可生物降解的湿气发电机制成",
      "url": "https://www.cpnn.com.cn/news/kj/202605/t20260526_1890544.html",
      "summary": "",
      "publishedAt": "2026-05-26",
      "source": "cpnn.com.cn"
    },
    {
      "id": "cpnn-t20260526_1890542",
      "title": "国网上海电力：加强具身智能机器人电力场景应用及成果转化",
      "url": "https://www.cpnn.com.cn/news/kj/202605/t20260526_1890542.html",
      "summary": "",
      "publishedAt": "2026-05-26",
      "source": "cpnn.com.cn"
    },
    {
      "id": "cpnn-t20260526_1890603",
      "title": "印尼苏门答腊“大停电”初步排除人为因素 电力系统恢复正常",
      "url": "https://www.cpnn.com.cn/news/gj/202605/t20260526_1890603.html",
      "summary": "",
      "publishedAt": "2026-05-26",
      "source": "cpnn.com.cn"
    },
    {
      "id": "cpnn-t20260526_1890470",
      "title": "国能大渡河枕头坝二级水电站首批机组投产发电",
      "url": "https://www.cpnn.com.cn/qiye/fadianPD2023/202605/t20260526_1890470.html",
      "summary": "",
      "publishedAt": "2026-05-26",
      "source": "cpnn.com.cn"
    },
    {
      "id": "cpnn-t20260526_1890483",
      "title": "国家能源集团深度参与2026国际氢能发展论坛",
      "url": "https://www.cpnn.com.cn/qiye/jishu2023/202605/t20260526_1890483.html",
      "summary": "",
      "publishedAt": "2026-05-26",
      "source": "cpnn.com.cn"
    },
    {
      "id": "cpnn-t20260526_1890610",
      "title": "大唐巩义发电公司尤祥光：十年磨一剑 今朝试锋芒",
      "url": "https://www.cpnn.com.cn/qiye/yingcai/202605/t20260526_1890610.html",
      "summary": "",
      "publishedAt": "2026-05-26",
      "source": "cpnn.com.cn"
    },
    {
      "id": "cpnn-t20260526_1890609",
      "title": "大唐巩义发电薛定国：煤海攻坚降本记",
      "url": "https://www.cpnn.com.cn/qiye/yingcai/202605/t20260526_1890609.html",
      "summary": "",
      "publishedAt": "2026-05-26",
      "source": "cpnn.com.cn"
    },
    {
      "id": "cpnn-t20260526_1890469",
      "title": "国家能源集团获中国企业财务数智化转型示范单位财务共享奖",
      "url": "https://www.cpnn.com.cn/qiye/rongyu/202605/t20260526_1890469.html",
      "summary": "",
      "publishedAt": "2026-05-26",
      "source": "cpnn.com.cn"
    },
    {
      "id": "cpnn-t20260522_1889792",
      "title": "预计最高16亿千瓦！国家发改委回应今夏电力保供形势",
      "url": "https://www.cpnn.com.cn/news/xwtt/202605/t20260522_1889792.html",
      "summary": "",
      "publishedAt": "2026-05-22",
      "source": "cpnn.com.cn"
    },
    {
      "id": "cpnn-t20260522_1889636",
      "title": "业界：发展生物质等清洁供热 助力农村能源低碳转型",
      "url": "https://www.cpnn.com.cn/news/baogao2023/202605/t20260522_1889636.html",
      "summary": "",
      "publishedAt": "2026-05-22",
      "source": "cpnn.com.cn"
    },
    {
      "id": "cpnn-t20260522_1889623",
      "title": "新型电网，将如何助力未来发展？",
      "url": "https://www.cpnn.com.cn/news/baogao2023/202605/t20260522_1889623.html",
      "summary": "",
      "publishedAt": "2026-05-22",
      "source": "cpnn.com.cn"
    },
    {
      "id": "cpnn-t20260522_1889681",
      "title": "节能风电总经理任职",
      "url": "https://www.cpnn.com.cn/news/renshi2023/202605/t20260522_1889681.html",
      "summary": "",
      "publishedAt": "2026-05-22",
      "source": "cpnn.com.cn"
    },
    {
      "id": "cpnn-t20260522_1889835",
      "title": "国家电投集团江西核电（天红科技）招聘公告",
      "url": "https://www.cpnn.com.cn/news/zhaopinxinxi2023/202605/t20260522_1889835.html",
      "summary": "",
      "publishedAt": "2026-05-22",
      "source": "cpnn.com.cn"
    },
    {
      "id": "cpnn-t20260522_1889652",
      "title": "大唐环境新能源设计高层次专业人才公开招聘",
      "url": "https://www.cpnn.com.cn/news/zhaopinxinxi2023/202605/t20260522_1889652.html",
      "summary": "",
      "publishedAt": "2026-05-22",
      "source": "cpnn.com.cn"
    },
    {
      "id": "cpnn-t20260522_1889909",
      "title": "国网石狮供电：科技赋能电网运维 智能巡视筑牢安全防线",
      "url": "https://www.cpnn.com.cn/qiye/dianwangPD2023/202605/t20260522_1889909.html",
      "summary": "",
      "publishedAt": "2026-05-22",
      "source": "cpnn.com.cn"
    },
    {
      "id": "cpnn-t20260522_1889800",
      "title": "南方电网公司以创新驱动打造数智计量体系",
      "url": "https://www.cpnn.com.cn/qiye/dianwangPD2023/202605/t20260522_1889800.html",
      "summary": "",
      "publishedAt": "2026-05-22",
      "source": "cpnn.com.cn"
    },
    {
      "id": "cpnn-t20260522_1889912",
      "title": "深化水电价格机制改革 服务能源安全与江河安澜战略",
      "url": "https://www.cpnn.com.cn/qiye/fadianPD2023/202605/t20260522_1889912.html",
      "summary": "",
      "publishedAt": "2026-05-22",
      "source": "cpnn.com.cn"
    },
    {
      "id": "cpnn-t20260521_1889502",
      "title": "荣盛集团、内蒙古能源集团等共同成立煤化工公司",
      "url": "https://www.cpnn.com.cn/news/mt/202605/t20260521_1889502.html",
      "summary": "",
      "publishedAt": "2026-05-21",
      "source": "cpnn.com.cn"
    },
    {
      "id": "cpnn-t20260521_1889442",
      "title": "构建面向未来的绿色能源体系，远景助力乌兰...",
      "url": "https://www.cpnn.com.cn/news/ydylnyhz/202605/t20260521_1889442.html",
      "summary": "",
      "publishedAt": "2026-05-21",
      "source": "cpnn.com.cn"
    },
    {
      "id": "cpnn-t20260521_1889487",
      "title": "中能观察丨降本破局 绿电直连“共享模式”落地",
      "url": "https://www.cpnn.com.cn/news/zngc/202605/t20260521_1889487.html",
      "summary": "",
      "publishedAt": "2026-05-21",
      "source": "cpnn.com.cn"
    },
    {
      "id": "cpnn-t20260521_1889474",
      "title": "国网武威供电开展新能源电网宽频振荡专题培训",
      "url": "https://www.cpnn.com.cn/qiye/dianwangPD2023/202605/t20260521_1889474.html",
      "summary": "",
      "publishedAt": "2026-05-21",
      "source": "cpnn.com.cn"
    },
    {
      "id": "cpnn-t20260521_1889450",
      "title": "大唐云南公司滇西新能源事业部王晓明：“三能”尖兵",
      "url": "https://www.cpnn.com.cn/qiye/yingcai/202605/t20260521_1889450.html",
      "summary": "",
      "publishedAt": "2026-05-21",
      "source": "cpnn.com.cn"
    },
    {
      "id": "cpnn-t20260520_1889180",
      "title": "绿电替代 助力地方传统产业蝶变",
      "url": "https://www.cpnn.com.cn/news/ydylnyhz/202605/t20260520_1889180.html",
      "summary": "",
      "publishedAt": "2026-05-20",
      "source": "cpnn.com.cn"
    },
    {
      "id": "cpnn-t20260519_1888590",
      "title": "北京绿电市场化交易规模首次超过火电",
      "url": "https://www.cpnn.com.cn/news/ydylnyhz/202605/t20260519_1888590.html",
      "summary": "",
      "publishedAt": "2026-05-19",
      "source": "cpnn.com.cn"
    },
    {
      "id": "cpnn-t20260519_1888611",
      "title": "三峡新能源副总经理张立一辞职",
      "url": "https://www.cpnn.com.cn/news/renshi2023/202605/t20260519_1888611.html",
      "summary": "",
      "publishedAt": "2026-05-19",
      "source": "cpnn.com.cn"
    },
    {
      "id": "cpnn-t20260428_1884153",
      "title": "国家能源集团大渡河老鹰岩二级水电站成功截流",
      "url": "https://www.cpnn.com.cn/qiye/fadianPD2023/202604/t20260428_1884153.html",
      "summary": "",
      "publishedAt": "2026-04-28",
      "source": "cpnn.com.cn"
    },
    {
      "id": "cpnn-t20260428_1884295",
      "title": "汛期将至，4月23日，大唐岩滩水力发电有限责任公司组织开展超标准洪水防洪调度应急预案实战化、全面性演练，以实景实训锤炼公司应急队伍。",
      "url": "https://www.cpnn.com.cn/qiye/anquan/202604/t20260428_1884295.html",
      "summary": "",
      "publishedAt": "2026-04-28",
      "source": "cpnn.com.cn"
    },
    {
      "id": "cpnn-t20260421_1882545",
      "title": "兰州倚能电力：植绿护绿践初心 凝心聚力促发展",
      "url": "https://www.cpnn.com.cn/qiye/yzfw/202604/t20260421_1882545.html",
      "summary": "",
      "publishedAt": "2026-04-21",
      "source": "cpnn.com.cn"
    },
    {
      "id": "cpnn-t20260414_1880730",
      "title": "大唐陈村水力发电公司推动学习教育走深见效",
      "url": "https://www.cpnn.com.cn/qiye/guanli/202604/t20260414_1880730.html",
      "summary": "",
      "publishedAt": "2026-04-14",
      "source": "cpnn.com.cn"
    },
    {
      "id": "cpnn-t20260410_1880238",
      "title": "塔山发电公司曹莎：锐意进取绽芳华",
      "url": "https://www.cpnn.com.cn/qiye/yingcai/202604/t20260410_1880238.html",
      "summary": "",
      "publishedAt": "2026-04-10",
      "source": "cpnn.com.cn"
    },
    {
      "id": "cpnn-t20220811_1541876",
      "title": "中国电力话语体系课题结题评审会在国网高培...",
      "url": "https://www.cpnn.com.cn/news/xwtopb/202208/t20220811_1541876.html",
      "summary": "",
      "publishedAt": "2022-08-11",
      "source": "cpnn.com.cn"
    },
    {
      "id": "cpnn-t20220715_1533884",
      "title": "国家电网公司召开2022年年中工作会议",
      "url": "https://www.cpnn.com.cn/news/nytt/202207/t20220715_1533884.html",
      "summary": "",
      "publishedAt": "2022-07-15",
      "source": "cpnn.com.cn"
    },
    {
      "id": "cpnn-t20220714_1533519",
      "title": "国家能源局党组部署开展第八轮巡视工作",
      "url": "https://www.cpnn.com.cn/news/nytt/202207/t20220714_1533519.html",
      "summary": "",
      "publishedAt": "2022-07-14",
      "source": "cpnn.com.cn"
    }
  ],
  "stats": {
    "articleCount": 65
  },
  "errors": []
}
