{
  "generatedAt": "2026-04-16T22:51:46+00:00",
  "parentFeed": "feed-digest.json",
  "filter": "central_china_provinces",
  "provinces": [
    "华中",
    "安徽",
    "江西",
    "河南",
    "湖北",
    "湖南"
  ],
  "articles": [
    {
      "id": "cpnn-t20260416_1881581",
      "title": "华中能源监管局全面升级区域中长期市场规则体系",
      "url": "https://www.cpnn.com.cn/news/nyjg/202604/t20260416_1881581.html",
      "summary": "",
      "publishedAt": "2026-04-16",
      "source": "cpnn.com.cn",
      "province": "华中"
    },
    {
      "id": "cpnn-t20260415_1881047",
      "title": "大唐河南清洁能源公司：实干让学习教育落地见效",
      "url": "https://www.cpnn.com.cn/qiye/guanli/202604/t20260415_1881047.html",
      "summary": "",
      "publishedAt": "2026-04-15",
      "source": "cpnn.com.cn",
      "province": "河南"
    },
    {
      "id": "cpnn-t20260415_1881048",
      "title": "大唐河南清洁能源公司：线塔上的“智斗计”",
      "url": "https://www.cpnn.com.cn/qiye/anquan/202604/t20260415_1881048.html",
      "summary": "",
      "publishedAt": "2026-04-15",
      "source": "cpnn.com.cn",
      "province": "河南"
    },
    {
      "id": "cpnn-t20260414_1880913",
      "title": "首届森林碳汇监测与认证论坛在武汉举行",
      "url": "https://www.cpnn.com.cn/qiye/jishu2023/202604/t20260414_1880913.html",
      "summary": "",
      "publishedAt": "2026-04-14",
      "source": "cpnn.com.cn",
      "province": "湖北"
    },
    {
      "id": "nea-20260414-d4a4be8b7cf1498fa6cee94792f81667-c",
      "title": "华中能源监管局推动强化电力市场运行监测和风险防控",
      "url": "https://www.nea.gov.cn/20260414/d4a4be8b7cf1498fa6cee94792f81667/c.html",
      "summary": "",
      "publishedAt": "2026-04-14",
      "source": "nea.gov.cn",
      "province": "华中"
    },
    {
      "id": "cpnn-t20260413_1880568",
      "title": "国能湖北公司年累计发电量突破100亿千瓦时",
      "url": "https://www.cpnn.com.cn/qiye/fadianPD2023/202604/t20260413_1880568.html",
      "summary": "",
      "publishedAt": "2026-04-13",
      "source": "cpnn.com.cn",
      "province": "湖北"
    },
    {
      "id": "nea-20260331-203488b39d454d76a3c9f04fce97eaca-c",
      "title": "国家能源局湖南监管办党组关于巡视“回头看”整改进展情况的通报",
      "url": "https://www.nea.gov.cn/20260331/203488b39d454d76a3c9f04fce97eaca/c.html",
      "summary": "",
      "publishedAt": "2026-03-31",
      "source": "nea.gov.cn",
      "province": "湖南"
    },
    {
      "id": "nea-20260331-1bf84fffaa9945c29cef4c144a04d8db-c",
      "title": "国家能源局华中监管局党组关于局党组第三轮巡视整改进展情况的通报",
      "url": "https://www.nea.gov.cn/20260331/1bf84fffaa9945c29cef4c144a04d8db/c.html",
      "summary": "",
      "publishedAt": "2026-03-31",
      "source": "nea.gov.cn",
      "province": "华中"
    },
    {
      "id": "cpnn-t20260324_1875457",
      "title": "大唐河南清洁能源杨明武：在平凡岗位书写不凡答卷",
      "url": "https://www.cpnn.com.cn/qiye/yingcai/202603/t20260324_1875457.html",
      "summary": "",
      "publishedAt": "2026-03-24",
      "source": "cpnn.com.cn",
      "province": "河南"
    }
  ],
  "stats": {
    "totalArticles": 9,
    "byProvince": {
      "华中": 3,
      "河南": 3,
      "湖北": 2,
      "湖南": 1
    }
  },
  "note": "Filtered subset of feed-digest.json that mentions 湖北/湖南/河南/江西/安徽 (or 华中) in the title. Month 2 roadmap feature. Consumers who only care about central-China energy news should subscribe to THIS feed instead of feed-digest.json."
}