{
  "generatedAt": "2026-06-04T23:14:47+00:00",
  "parentFeed": "feed-digest.json",
  "filter": "central_china_provinces",
  "provinces": [
    "华中",
    "安徽",
    "江西",
    "河南",
    "湖北",
    "湖南"
  ],
  "articles": [
    {
      "id": "cpnn-t20260604_1893023",
      "title": "华中能源监管局组织召开油气管网设施公平开放工作协调会",
      "url": "https://www.cpnn.com.cn/news/nyjg/202606/t20260604_1893023.html",
      "summary": "",
      "publishedAt": "2026-06-04",
      "source": "cpnn.com.cn",
      "province": "华中"
    },
    {
      "id": "cpnn-t20260604_1892963",
      "title": "皖能马鞍山发电“火力全开”备战迎峰度夏",
      "url": "https://www.cpnn.com.cn/qiye/fadianPD2023/202606/t20260604_1892963.html",
      "summary": "",
      "publishedAt": "2026-06-04",
      "source": "cpnn.com.cn",
      "province": "安徽"
    },
    {
      "id": "cpnn-t20260604_1892965",
      "title": "大唐安徽淮北发电1号机组再度获评中电联AAAA级称号",
      "url": "https://www.cpnn.com.cn/qiye/rongyu/202606/t20260604_1892965.html",
      "summary": "",
      "publishedAt": "2026-06-04",
      "source": "cpnn.com.cn",
      "province": "安徽"
    },
    {
      "id": "cpnn-t20260603_1892642",
      "title": "江西电力中长期市场6月起每日开市",
      "url": "https://www.cpnn.com.cn/news/dianli2023/202606/t20260603_1892642.html",
      "summary": "",
      "publishedAt": "2026-06-03",
      "source": "cpnn.com.cn",
      "province": "江西"
    },
    {
      "id": "nea-20260602-0d5bb79e7edf4c59b73d859f5830ae19-c",
      "title": "华中能源监管局组织召开新型经营主体参与电力市场工作座谈会",
      "url": "https://www.nea.gov.cn/20260602/0d5bb79e7edf4c59b73d859f5830ae19/c.html",
      "summary": "",
      "publishedAt": "2026-06-02",
      "source": "nea.gov.cn",
      "province": "华中"
    },
    {
      "id": "cpnn-t20260522_1889835",
      "title": "国家电投集团江西核电（天红科技）招聘公告",
      "url": "https://www.cpnn.com.cn/news/zhaopinxinxi2023/202605/t20260522_1889835.html",
      "summary": "",
      "publishedAt": "2026-05-22",
      "source": "cpnn.com.cn",
      "province": "江西"
    },
    {
      "id": "nea-20260331-203488b39d454d76a3c9f04fce97eaca-c",
      "title": "国家能源局湖南监管办党组关于巡视“回头看”整改进展情况的通报",
      "url": "https://www.nea.gov.cn/20260331/203488b39d454d76a3c9f04fce97eaca/c.html",
      "summary": "",
      "publishedAt": "2026-03-31",
      "source": "nea.gov.cn",
      "province": "湖南"
    },
    {
      "id": "nea-20260331-1bf84fffaa9945c29cef4c144a04d8db-c",
      "title": "国家能源局华中监管局党组关于局党组第三轮巡视整改进展情况的通报",
      "url": "https://www.nea.gov.cn/20260331/1bf84fffaa9945c29cef4c144a04d8db/c.html",
      "summary": "",
      "publishedAt": "2026-03-31",
      "source": "nea.gov.cn",
      "province": "华中"
    }
  ],
  "stats": {
    "totalArticles": 8,
    "byProvince": {
      "华中": 3,
      "安徽": 2,
      "江西": 2,
      "湖南": 1
    }
  },
  "note": "Filtered subset of feed-digest.json that mentions 湖北/湖南/河南/江西/安徽 (or 华中) in the title. Month 2 roadmap feature. Consumers who only care about central-China energy news should subscribe to THIS feed instead of feed-digest.json."
}