{
  "source": "ne21.com",
  "sourceName": "世纪新能源网",
  "generatedAt": "2026-07-11T21:21:20+00:00",
  "lookbackHours": 48,
  "articles": [
    {
      "id": "ne21-228906",
      "title": "设立10亿并购基金盘活存量资产，碧澄能源以西南总部为支点加速优质新能源资产集聚",
      "url": "https://www.ne21.com/news/show-228906.html",
      "summary": "",
      "publishedAt": null,
      "source": "ne21.com"
    },
    {
      "id": "ne21-228904",
      "title": "正式调频交易！盛弘日本储能项目投运，迈入商业化验证新阶段",
      "url": "https://www.ne21.com/news/show-228904.html",
      "summary": "",
      "publishedAt": null,
      "source": "ne21.com"
    },
    {
      "id": "ne21-228903",
      "title": "直击越南展丨弘正储能以场景化方案加速布局东南亚市场",
      "url": "https://www.ne21.com/news/show-228903.html",
      "summary": "",
      "publishedAt": null,
      "source": "ne21.com"
    },
    {
      "id": "ne21-228902",
      "title": "储能系统哪家好？利星能TRITON-6251以“光储同寿”重新定义25年价值周期",
      "url": "https://www.ne21.com/news/show-228902.html",
      "summary": "",
      "publishedAt": null,
      "source": "ne21.com"
    }
  ],
  "stats": {
    "articleCount": 4
  },
  "errors": []
}
